Workbook
Name _DLX1.INC: Haver!$2:$11
Name _DLX2.INC: Haver_M!$2:$11
Name _DLX3.INC: UK_HAVER!$1:$13
Name Data: [1]sheet0!$C$2

Sheet matlab
A1: date | B1: EZGDP | C1: USGDP | D1: UKGDP | E1: CHGDP | F1: EZCPI | G1: USCPI | H1: UKCPI | I1: CHCPI | J1: EZRR | K1: USRR | L1: UKRR | M1: CHRR | N1: USDEUR | O1: USDGBP | P1: USDCNY | Q1: VIX | R1: POIL | S1: EZ10Y
A2: 29281 | B2: =AWM!B42 -> 1561462.5 | C2: =Haver!D12 -> 1835.4 | D2: =UK_HAVER!C14 -> 290378 | E2: =E3/(OEM!E8/OEM!E7) -> 711.63119 | F2: =AWM!D42 -> 33.126531 | G2: =Haver!N12 -> 79.033333 | H2: =UK_HAVER!E14 -> #N/A | J2: =AWM!C42 -> 12.735107 | K2: =OEM!D7 -> 13.93896 | L2: =UK_HAVER!D14 -> 17 | M2: =M3/(OEM_aux!B8/OEM_aux!B7) -> 4.4873495 | N2: =Haver!J12 -> 0.70891484 | O2: =1/UK_HAVER!F14 -> 0.44393803 | P2: =1/ '[2]Exchange rate'!$C7 -> 0.0058788256
A3: 29373 | B3: =AWM!B43 -> 1554130.5 | C3: =Haver!D13 -> 1797.6 | D3: =UK_HAVER!C15 -> 284713 | E3: =E4/(OEM!E9/OEM!E8) -> 726.11643 | F3: =AWM!D43 -> 33.986161 | G3: =Haver!N13 -> 81.7 | H3: =UK_HAVER!E15 -> #N/A | J3: =AWM!C43 -> 13.23709 | K3: =OEM!D8 -> 11.7426 | L3: =UK_HAVER!D15 -> 17 | M3: =M4/(OEM_aux!B9/OEM_aux!B8) -> 4.4873495 | N3: =Haver!J13 -> 0.71904683 | O3: =1/UK_HAVER!F15 -> 0.4381289 | P3: =1/ '[2]Exchange rate'!$C8 -> 0.005810663 | S3: =Mater_Q!B4 -> 8.7113333
A4: 29465 | B4: =AWM!B44 -> 1553244.6 | C4: =Haver!D14 -> 1795.4 | D4: =UK_HAVER!C16 -> 284402 | E4: =E5/(OEM!E10/OEM!E9) -> 740.12672 | F4: =AWM!D44 -> 34.767567 | G4: =Haver!N14 -> 83.233333 | H4: =UK_HAVER!E16 -> #N/A | J4: =AWM!C44 -> 12.239029 | K4: =OEM!D9 -> 9.094363 | L4: =UK_HAVER!D16 -> 16.03 | M4: =M5/(OEM_aux!B10/OEM_aux!B9) -> 4.4873495 | N4: =Haver!J14 -> 0.70283289 | O4: =1/UK_HAVER!F16 -> 0.41988579 | P4: =1/ '[2]Exchange rate'!$C9 -> 0.0057418828 | S4: =Mater_Q!B5 -> 7.989
A5: 29556 | B5: =AWM!B45 -> 1553974.2 | C5: =Haver!D15 -> 1828.9 | D5: =UK_HAVER!C17 -> 281496 | E5: =E6/(OEM!E11/OEM!E10) -> 755.51459 | F5: =AWM!D45 -> 35.621301 | G5: =Haver!N15 -> 85.566667 | H5: =UK_HAVER!E17 -> #N/A | J5: =AWM!C45 -> 12.663299 | K5: =OEM!D10 -> 14.72999 | L5: =UK_HAVER!D17 -> 15.2 | M5: =M6/(OEM_aux!B11/OEM_aux!B10) -> 4.4873495 | N5: =Haver!J15 -> 0.74632621 | O5: =1/UK_HAVER!F17 -> 0.41919933 | P5: =1/ '[2]Exchange rate'!$C10 -> 0.0058378513 | S5: =Mater_Q!B6 -> 8.642
A6: 29646 | B6: =AWM!B46 -> 1555473.6 | C6: =Haver!D16 -> 1864.8 | D6: =UK_HAVER!C18 -> 281257 | E6: =E7/(OEM!E12/OEM!E11) -> 746.28871 | F6: =AWM!D46 -> 36.78482 | G6: =Haver!N16 -> 87.933333 | H6: =UK_HAVER!E18 -> #N/A | J6: =AWM!C46 -> 13.432882 | K6: =OEM!D11 -> 15.40231 | L6: =UK_HAVER!D18 -> 13.546667 | M6: =M7/(OEM_aux!B12/OEM_aux!B11) -> 4.4873495 | N6: =Haver!J16 -> 0.81110895 | O6: =1/UK_HAVER!F18 -> 0.43296916 | P6: =1/ '[2]Exchange rate'!$C11 -> 0.0060103992 | S6: =Mater_Q!B7 -> 9.6076667
A7: 29738 | B7: =AWM!B47 -> 1560133.1 | C7: =Haver!D17 -> 1850.9 | D7: =UK_HAVER!C19 -> 282155 | E7: =E8/(OEM!E13/OEM!E12) -> 762.60048 | F7: =AWM!D47 -> 37.768239 | G7: =Haver!N17 -> 89.766667 | H7: =UK_HAVER!E19 -> #N/A | J7: =AWM!C47 -> 15.507875 | K7: =OEM!D12 -> 16.51873 | L7: =UK_HAVER!D19 -> 12 | M7: =M8/(OEM_aux!B13/OEM_aux!B12) -> 4.4873495 | N7: =Haver!J17 -> 0.89624206 | O7: =1/UK_HAVER!F19 -> 0.48096192 | P7: =1/ '[2]Exchange rate'!$C12 -> 0.0061633814 | S7: =Mater_Q!B8 -> 10.304333
A8: 29830 | B8: =AWM!B48 -> 1564437.5 | C8: =Haver!D18 -> 1873.1 | D8: =UK_HAVER!C20 -> 285437 | E8: =E9/(OEM!E14/OEM!E13) -> 778.4717 | F8: =AWM!D48 -> 38.724472 | G8: =Haver!N18 -> 92.266667 | H8: =UK_HAVER!E20 -> #N/A | J8: =AWM!C48 -> 16.133415 | K8: =OEM!D13 -> 16.47078 | L8: =UK_HAVER!D20 -> 12.513333 | M8: =M9/(OEM_aux!B14/OEM_aux!B13) -> 4.4873495 | N8: =Haver!J18 -> 0.96849799 | O8: =1/UK_HAVER!F20 -> 0.54460298 | P8: =1/ '[2]Exchange rate'!$C13 -> 0.006081741 | S8: =Mater_Q!B9 -> 10.558667
A9: 29921 | B9: =AWM!B49 -> 1568108.4 | C9: =Haver!D19 -> 1852.7 | D9: =UK_HAVER!C21 -> 285814 | E9: =E10/(OEM!E15/OEM!E14) -> 795.75611 | F9: =AWM!D49 -> 39.745347 | G9: =Haver!N19 -> 93.766667 | H9: =UK_HAVER!E21 -> #N/A | J9: =AWM!C49 -> 15.426309 | K9: =OEM!D14 -> 12.66561 | L9: =UK_HAVER!D21 -> 14.61 | M9: =M10/(OEM_aux!B15/OEM_aux!B14) -> 4.4873495 | N9: =Haver!J19 -> 0.91801513 | O9: =1/UK_HAVER!F21 -> 0.53130258 | P9: =1/ '[2]Exchange rate'!$C14 -> 0.0060732605 | S9: =Mater_Q!B10 -> 9.9646667
A10: 30011 | B10: =AWM!B50 -> 1574589.1 | C10: =Haver!D20 -> 1823.9 | D10: =UK_HAVER!C22 -> 286275 | E10: =E11/(OEM!E16/OEM!E15) -> 811.15802 | F10: =AWM!D50 -> 40.729084 | G10: =Haver!N20 -> 94.6 | H10: =UK_HAVER!E22 -> #N/A | J10: =AWM!C50 -> 14.331319 | K10: =OEM!D15 -> 13.27632 | L10: =UK_HAVER!D22 -> 13.793333 | M10: =M11/(OEM_aux!B16/OEM_aux!B15) -> 7.2833131 | N10: =Haver!J20 -> 0.96385852 | O10: =1/UK_HAVER!F22 -> 0.54168247 | P10: =1/ '[2]Exchange rate'!$C15 -> 0.0060699612 | S10: =Mater_Q!B11 -> 9.6733333
A11: 30103 | B11: =AWM!B51 -> 1576706.9 | C11: =Haver!D21 -> 1832.2 | D11: =UK_HAVER!C23 -> 289232 | E11: =E12/(OEM!E17/OEM!E16) -> 829.90071 | F11: =AWM!D51 -> 41.674783 | G11: =Haver!N21 -> 95.966667 | H11: =UK_HAVER!E23 -> #N/A | J11: =AWM!C51 -> 14.400041 | K11: =OEM!D16 -> 13.51189 | L11: =UK_HAVER!D23 -> 13.016667 | M11: =M12/(OEM_aux!B17/OEM_aux!B16) -> 7.2833131 | N11: =Haver!J21 -> 0.99683737 | O11: =1/UK_HAVER!F23 -> 0.56193455 | P11: =1/ '[2]Exchange rate'!$C16 -> 0.0060194259 | S11: =Mater_Q!B12 -> 8.9833333
A12: 30195 | B12: =AWM!B52 -> 1568297.1 | C12: =Haver!D22 -> 1825.2 | D12: =UK_HAVER!C24 -> 289852 | E12: =E13/(OEM!E18/OEM!E17) -> 849.51646 | F12: =AWM!D52 -> 42.478199 | G12: =Haver!N22 -> 97.633333 | H12: =UK_HAVER!E24 -> #N/A | J12: =AWM!C52 -> 13.349537 | K12: =Haver!H22 -> 10.25 | L12: =UK_HAVER!D24 -> 11.353333 | M12: =M13/(OEM_aux!B18/OEM_aux!B17) -> 7.2833131 | N12: =Haver!J22 -> 1.0519222 | O12: =1/UK_HAVER!F24 -> 0.58000155 | P12: =1/ '[2]Exchange rate'!$C17 -> 0.0060098971 | S12: =Mater_Q!B13 -> 8.9873333
A13: 30286 | B13: =AWM!B53 -> 1568970 | C13: =Haver!D23 -> 1826 | D13: =UK_HAVER!C25 -> 291832 | E13: =E14/(OEM!E19/OEM!E18) -> 869.93506 | F13: =AWM!D53 -> 43.293676 | G13: =Haver!N23 -> 97.933333 | H13: =UK_HAVER!E25 -> #N/A | J13: =AWM!C53 -> 12.606617 | K13: =Haver!H23 -> 8.5 | L13: =UK_HAVER!D25 -> 9.6833333 | M13: =M14/(OEM_aux!B19/OEM_aux!B18) -> 7.2833131 | N13: =Haver!J23 -> 1.0711849 | O13: =1/UK_HAVER!F25 -> 0.6067593 | P13: =1/ '[2]Exchange rate'!$C18 -> 0.0059951463 | S13: =Mater_Q!B14 -> 8.2193333
A14: 30376 | B14: =AWM!B54 -> 1579416.4 | C14: =Haver!D24 -> 1850 | D14: =UK_HAVER!C26 -> 297563 | E14: =E15/(OEM!E20/OEM!E19) -> 895.49387 | F14: =AWM!D54 -> 44.173742 | G14: =Haver!N24 -> 98 | H14: =UK_HAVER!E26 -> #N/A | J14: =AWM!C54 -> 11.886462 | K14: =Haver!H24 -> 8.625 | L14: =UK_HAVER!D26 -> 10.816667 | M14: =M15/(OEM_aux!B20/OEM_aux!B19) -> 7.2833131 | N14: =Haver!J24 -> 1.0548208 | O14: =1/UK_HAVER!F26 -> 0.65238665 | P14: =1/ '[2]Exchange rate'!$C19 -> 0.0059405599 | S14: =Mater_Q!B15 -> 7.6146667
A15: 30468 | B15: =AWM!B55 -> 1589751.1 | C15: =Haver!D25 -> 1892.1 | D15: =UK_HAVER!C27 -> 299623 | E15: =E16/(OEM!E21/OEM!E20) -> 918.24915 | F15: =AWM!D55 -> 44.935485 | G15: =Haver!N25 -> 99.133333 | H15: =UK_HAVER!E27 -> #N/A | J15: =AWM!C55 -> 11.847545 | K15: =Haver!H25 -> 9 | L15: =UK_HAVER!D27 -> 10.016667 | M15: =M16/(OEM_aux!B21/OEM_aux!B20) -> 7.2833131 | N15: =Haver!J25 -> 1.0964135 | O15: =1/UK_HAVER!F27 -> 0.64428838 | P15: =1/ '[2]Exchange rate'!$C20 -> 0.0058727631 | S15: =Mater_Q!B16 -> 7.7703333
A16: 30560 | B16: =AWM!B56 -> 1593881.2 | C16: =Haver!D26 -> 1929.9 | D16: =UK_HAVER!C28 -> 303085 | E16: =E17/(OEM!E22/OEM!E21) -> 942.61391 | F16: =AWM!D56 -> 45.68737 | G16: =Haver!N26 -> 100.1 | H16: =UK_HAVER!E28 -> #N/A | J16: =AWM!C56 -> 12.21865 | K16: =Haver!H26 -> 9.375 | L16: =UK_HAVER!D28 -> 9.56 | M16: =M17/(OEM_aux!B22/OEM_aux!B21) -> 7.2833131 | N16: =Haver!J26 -> 1.1613215 | O16: =1/UK_HAVER!F28 -> 0.66247102 | P16: =1/ '[2]Exchange rate'!$C21 -> 0.0056806014 | S16: =Mater_Q!B17 -> 8.361
A17: 30651 | B17: =AWM!B57 -> 1611312.5 | C17: =Haver!D27 -> 1970.2 | D17: =UK_HAVER!C29 -> 305361 | E17: =E18/(OEM!E23/OEM!E22) -> 965.49596 | F17: =AWM!D57 -> 46.475521 | G17: =Haver!N27 -> 101.1 | H17: =UK_HAVER!E29 -> #N/A | J17: =AWM!C57 -> 12.169143 | K17: =Haver!H27 -> 9.375 | L17: =UK_HAVER!D29 -> 9.06 | M17: =M18/(OEM_aux!B23/OEM_aux!B22) -> 7.2833131 | N17: =Haver!J27 -> 1.1850185 | O17: =1/UK_HAVER!F29 -> 0.68068886 | P17: =1/ '[2]Exchange rate'!$C22 -> 0.0055921406 | S17: =Mater_Q!B18 -> 8.3263333
A18: 30742 | B18: =AWM!B58 -> 1625156.1 | C18: =Haver!D28 -> 2008.7 | D18: =UK_HAVER!C30 -> 307964 | E18: =E19/(OEM!E24/OEM!E23) -> 1029.5956 | F18: =AWM!D58 -> 47.308976 | G18: =Haver!N28 -> 102.53333 | H18: =UK_HAVER!E30 -> #N/A | J18: =AWM!C58 -> 11.43169 | K18: =Haver!H28 -> 10.5 | L18: =UK_HAVER!D30 -> 8.9433333 | M18: =M19/(OEM_aux!B24/OEM_aux!B23) -> 7.2833131 | N18: =Haver!J28 -> 1.2024318 | O18: =1/UK_HAVER!F30 -> 0.69686411 | P18: =1/ '[2]Exchange rate'!$C23 -> 0.0057242328 | S18: =Mater_Q!B19 -> 8.2333333
A19: 30834 | B19: =AWM!B59 -> 1617476.5 | C19: =Haver!D29 -> 2043.4 | D19: =UK_HAVER!C31 -> 304892 | E19: =E20/(OEM!E25/OEM!E24) -> 1056.8872 | F19: =AWM!D59 -> 47.937614 | G19: =Haver!N29 -> 103.5 | H19: =UK_HAVER!E31 -> #N/A | I19: =reconstruct_levels_ch!D19 -> 16.953213 | J19: =AWM!C59 -> 10.857933 | K19: =Haver!H29 -> 10.5 | L19: =UK_HAVER!D31 -> 8.8433333 | M19: =M20/(OEM_aux!B25/OEM_aux!B24) -> 7.2833131 | N19: =Haver!J29 -> 1.2116977 | O19: =1/UK_HAVER!F31 -> 0.71643502 | P19: =1/ '[2]Exchange rate'!$C24 -> 0.0059476264 | S19: =Mater_Q!B20 -> 8.188
A20: 30926 | B20: =AWM!B60 -> 1634152.6 | C20: =Haver!D30 -> 2063.1 | D20: =UK_HAVER!C32 -> 307122 | E20: =E21/(OEM!E26/OEM!E25) -> 1086.3049 | F20: =AWM!D60 -> 48.424678 | G20: =Haver!N30 -> 104.4 | H20: =UK_HAVER!E32 -> #N/A | I20: =reconstruct_levels_ch!D20 -> 17.05617 | J20: =AWM!C60 -> 10.413573 | K20: =Haver!H30 -> 11 | L20: =UK_HAVER!D32 -> 10.89 | M20: =M21/(OEM_aux!B26/OEM_aux!B25) -> 7.2833131 | N20: =Haver!J30 -> 1.3025972 | O20: =1/UK_HAVER!F32 -> 0.77130737 | P20: =1/ '[2]Exchange rate'!$C25 -> 0.006309626 | S20: =Mater_Q!B21 -> 8.0836667
A21: 31017 | B21: =AWM!B61 -> 1642515.5 | C21: =Haver!D31 -> 2080.1 | D21: =UK_HAVER!C33 -> 312697 | E21: =E22/(OEM!E27/OEM!E26) -> 1113.4679 | F21: =AWM!D61 -> 49.042148 | G21: =Haver!N31 -> 105.3 | H21: =UK_HAVER!E33 -> #N/A | I21: =reconstruct_levels_ch!D21 -> 17.209847 | J21: =AWM!C61 -> 10.128111 | K21: =Haver!H31 -> 8.125 | L21: =UK_HAVER!D33 -> 9.9533333 | M21: =M22/(OEM_aux!B27/OEM_aux!B26) -> 7.2833131 | N21: =Haver!J31 -> 1.3673007 | O21: =1/UK_HAVER!F33 -> 0.82306785 | P21: =1/ '[2]Exchange rate'!$C26 -> 0.0067990209 | S21: =Mater_Q!B22 -> 7.29
A22: 31107 | B22: =AWM!B62 -> 1646206.4 | C22: =Haver!D32 -> 2100.2 | D22: =UK_HAVER!C34 -> 315753 | E22: =E23/(OEM!E28/OEM!E27) -> 1166.2879 | F22: =AWM!D62 -> 49.862985 | G22: =Haver!N32 -> 106.26667 | H22: =UK_HAVER!E34 -> #N/A | I22: =reconstruct_levels_ch!D22 -> 17.915297 | J22: =AWM!C62 -> 9.8634286 | K22: =Haver!H32 -> 8.5 | L22: =UK_HAVER!D34 -> 12.966667 | M22: =M23/(OEM_aux!B28/OEM_aux!B27) -> 7.2833131 | N22: =Haver!J32 -> 1.4618729 | O22: =1/UK_HAVER!F34 -> 0.89672695 | P22: =1/ '[2]Exchange rate'!$C27 -> 0.0068723043 | S22: =Mater_Q!B23 -> 7.4443333
A23: 31199 | B23: =AWM!B63 -> 1661914.3 | C23: =Haver!D33 -> 2118.7 | D23: =UK_HAVER!C35 -> 322451 | E23: =E24/(OEM!E29/OEM!E28) -> 1199.0291 | F23: =AWM!D63 -> 50.535072 | G23: =Haver!N33 -> 107.23333 | H23: =UK_HAVER!E35 -> #N/A | I23: =reconstruct_levels_ch!D23 -> 18.539499 | J23: =AWM!C63 -> 9.9615894 | K23: =Haver!H33 -> 7.75 | L23: =UK_HAVER!D35 -> 12.48 | M23: =M24/(OEM_aux!B29/OEM_aux!B28) -> 8.215301 | N23: =Haver!J33 -> 1.3773757 | O23: =1/UK_HAVER!F35 -> 0.79643198 | P23: =1/ '[2]Exchange rate'!$C28 -> 0.0069632937 | S23: =Mater_Q!B24 -> 7.1856667
A24: 31291 | B24: =AWM!B64 -> 1675982.7 | C24: =Haver!D34 -> 2151.1 | D24: =UK_HAVER!C36 -> 322392 | E24: =E25/(OEM!E30/OEM!E29) -> 1231.711 | F24: =AWM!D64 -> 50.78839 | G24: =Haver!N34 -> 107.9 | H24: =UK_HAVER!E36 -> #N/A | I24: =reconstruct_levels_ch!D24 -> 18.959105 | J24: =AWM!C64 -> 9.3468045 | K24: =Haver!H34 -> 8 | L24: =UK_HAVER!D36 -> 11.573333 | M24: =M25/(OEM_aux!B30/OEM_aux!B29) -> 8.215301 | N24: =Haver!J34 -> 1.2739995 | O24: =1/UK_HAVER!F36 -> 0.72656818 | P24: =1/ '[2]Exchange rate'!$C29 -> 0.00721368 | S24: =Mater_Q!B25 -> 6.616
A25: 31382 | B25: =AWM!B65 -> 1685974.7 | C25: =Haver!D35 -> 2167.1 | D25: =UK_HAVER!C37 -> 322604 | E25: =E26/(OEM!E31/OEM!E30) -> 1261.5479 | F25: =AWM!D65 -> 51.210371 | G25: =Haver!N35 -> 109 | H25: =UK_HAVER!E37 -> #N/A | I25: =reconstruct_levels_ch!D25 -> 19.139532 | J25: =AWM!C65 -> 8.627972 | K25: =Haver!H35 -> 7.75 | L25: =UK_HAVER!D37 -> 11.38 | M25: =M26/(OEM_aux!B31/OEM_aux!B30) -> 8.215301 | N25: =Haver!J35 -> 1.1713136 | O25: =1/UK_HAVER!F37 -> 0.69673464 | P25: =1/ '[2]Exchange rate'!$C30 -> 0.0080715006 | S25: =Mater_Q!B26 -> 6.5403333
A26: 31472 | B26: =AWM!B66 -> 1680223 | C26: =Haver!D36 -> 2187.3 | D26: =UK_HAVER!C38 -> 325968 | E26: =E27/(OEM!E32/OEM!E31) -> 1271.571 | F26: =AWM!D66 -> 51.615763 | G26: =Haver!N36 -> 109.56667 | H26: =UK_HAVER!E38 -> #N/A | I26: =reconstruct_levels_ch!D26 -> 19.369935 | J26: =AWM!C66 -> 8.7486202 | K26: =Haver!H36 -> 7.25 | L26: =UK_HAVER!D38 -> 12.12 | M26: =M27/(OEM_aux!B32/OEM_aux!B31) -> 8.215301 | N26: =Haver!J36 -> 1.0817094 | O26: =1/UK_HAVER!F38 -> 0.6942034 | P26: =1/ '[2]Exchange rate'!$C31 -> 0.0083729093 | S26: =Mater_Q!B27 -> 6.095
A27: 31564 | B27: =AWM!B67 -> 1711030.4 | C27: =Haver!D37 -> 2197.1 | D27: =UK_HAVER!C39 -> 328872 | E27: =E28/(OEM!E33/OEM!E32) -> 1306.9911 | F27: =AWM!D67 -> 51.818958 | G27: =Haver!N37 -> 109.03333 | H27: =UK_HAVER!E39 -> #N/A | I27: =reconstruct_levels_ch!D27 -> 19.422583 | J27: =AWM!C67 -> 8.0283937 | K27: =Haver!H37 -> 6.875 | L27: =UK_HAVER!D39 -> 10.326667 | M27: =M28/(OEM_aux!B33/OEM_aux!B32) -> 8.215301 | N27: =Haver!J37 -> 1.0427982 | O27: =1/UK_HAVER!F39 -> 0.66252954 | P27: =1/ '[2]Exchange rate'!$C32 -> 0.0084876602 | S27: =Mater_Q!B28 -> 5.6593333
A28: 31656 | B28: =AWM!B68 -> 1719722.7 | C28: =Haver!D38 -> 2218.2 | D28: =UK_HAVER!C40 -> 330966 | E28: =E29/(OEM!E34/OEM!E33) -> 1340.2188 | F28: =AWM!D68 -> 51.961723 | G28: =Haver!N38 -> 109.7 | H28: =UK_HAVER!E40 -> #N/A | I28: =reconstruct_levels_ch!D28 -> 19.737391 | J28: =AWM!C68 -> 7.7533413 | K28: =Haver!H38 -> 5.875 | L28: =UK_HAVER!D40 -> 9.88 | M28: =M29/(OEM_aux!B34/OEM_aux!B33) -> 8.215301 | N28: =Haver!J38 -> 0.98696515 | O28: =1/UK_HAVER!F40 -> 0.67219359 | P28: =1/ '[2]Exchange rate'!$C33 -> 0.0099288794 | R28: =Haver!R38 -> 12.316667 | S28: =Mater_Q!B29 -> 5.731
A29: 31747 | B29: =AWM!B69 -> 1723981.4 | C29: =Haver!D39 -> 2230.1 | D29: =UK_HAVER!C41 -> 337367 | E29: =E30/(OEM!E35/OEM!E34) -> 1371.7743 | F29: =AWM!D69 -> 52.142784 | G29: =Haver!N39 -> 110.46667 | H29: =UK_HAVER!E41 -> #N/A | I29: =reconstruct_levels_ch!D29 -> 20.219317 | J29: =AWM!C69 -> 7.8747736 | K29: =Haver!H39 -> 5.875 | L29: =UK_HAVER!D41 -> 10.733333 | M29: =M30/(OEM_aux!B35/OEM_aux!B34) -> 8.215301 | N29: =Haver!J39 -> 0.96334164 | O29: =1/UK_HAVER!F41 -> 0.69938221 | P29: =1/ '[2]Exchange rate'!$C34 -> 0.0099319266 | R29: =Haver!R39 -> 14.676667 | S29: =Mater_Q!B30 -> 6.0893333
A30: 31837 | B30: =AWM!B70 -> 1715707.6 | C30: =Haver!D40 -> 2246.6 | D30: =UK_HAVER!C42 -> 339754 | E30: =E31/(OEM!E36/OEM!E35) -> 1422.764 | F30: =AWM!D70 -> 52.622287 | G30: =Haver!N40 -> 111.8 | H30: =UK_HAVER!E42 -> #N/A | I30: =reconstruct_levels_ch!D30 -> 20.472642 | J30: =AWM!C70 -> 8.105353 | K30: =Haver!H40 -> 6 | L30: =UK_HAVER!D42 -> 10.673333 | M30: =M31/(OEM_aux!B36/OEM_aux!B35) -> 8.215301 | N30: =Haver!J40 -> 0.88926304 | O30: =1/UK_HAVER!F42 -> 0.64855049 | P30: =1/ '[2]Exchange rate'!$C35 -> 0.010162573 | R30: =Haver!R40 -> 17.87 | S30: =Mater_Q!B31 -> 5.9233333
A31: 31929 | B31: =AWM!B71 -> 1744613 | C31: =Haver!D41 -> 2270.8 | D31: =UK_HAVER!C43 -> 344795 | E31: =E32/(OEM!E37/OEM!E36) -> 1462.3531 | F31: =AWM!D71 -> 52.976874 | G31: =Haver!N41 -> 113.06667 | H31: =UK_HAVER!E43 -> #N/A | I31: =reconstruct_levels_ch!D31 -> 20.903646 | J31: =AWM!C71 -> 8.4258269 | K31: =Haver!H41 -> 6.75 | L31: =UK_HAVER!D43 -> 9.22 | M31: =M32/(OEM_aux!B37/OEM_aux!B36) -> 8.215301 | N31: =Haver!J41 -> 0.86945685 | O31: =1/UK_HAVER!F43 -> 0.60892687 | P31: =1/ '[2]Exchange rate'!$C36 -> 0.010301683 | R31: =Haver!R41 -> 18.666667 | S31: =Mater_Q!B32 -> 5.664
A32: 32021 | B32: =AWM!B72 -> 1763348.5 | C32: =Haver!D42 -> 2290.5 | D32: =UK_HAVER!C44 -> 353365 | E32: =E33/(OEM!E38/OEM!E37) -> 1495.7588 | F32: =AWM!D72 -> 53.247483 | G32: =Haver!N42 -> 114.26667 | H32: =UK_HAVER!E44 -> #N/A | I32: =reconstruct_levels_ch!D32 -> 21.244332 | J32: =AWM!C72 -> 8.4902365 | K32: =Haver!H42 -> 7.3125 | L32: =UK_HAVER!D44 -> 9.4966667 | M32: =M33/(OEM_aux!B38/OEM_aux!B37) -> 8.215301 | N32: =Haver!J42 -> 0.88626292 | O32: =1/UK_HAVER!F44 -> 0.61814885 | P32: =1/ '[2]Exchange rate'!$C37 -> 0.010120805 | R32: =Haver!R42 -> 19.05 | S32: =Mater_Q!B33 -> 6.4276667
A33: 32112 | B33: =AWM!B73 -> 1785825.7 | C33: =Haver!D43 -> 2329.8 | D33: =UK_HAVER!C45 -> 357439 | E33: =E34/(OEM!E39/OEM!E38) -> 1528.3625 | F33: =AWM!D73 -> 53.521776 | G33: =Haver!N43 -> 115.33333 | H33: =UK_HAVER!E45 -> #N/A | I33: =reconstruct_levels_ch!D33 -> 21.837013 | J33: =AWM!C73 -> 8.4260121 | K33: =Haver!H43 -> 6.8125 | L33: =UK_HAVER!D45 -> 9.0266667 | M33: =M34/(OEM_aux!B39/OEM_aux!B38) -> 8.215301 | N33: =Haver!J43 -> 0.8235039 | O33: =1/UK_HAVER!F45 -> 0.56967073 | P33: =1/ '[2]Exchange rate'!$C38 -> 0.010350157 | R33: =Haver!R43 -> 17.863333 | S33: =Mater_Q!B34 -> 6.5503333
A34: 32203 | B34: =AWM!B74 -> 1795687 | C34: =Haver!D44 -> 2341.9 | D34: =UK_HAVER!C46 -> 363267 | E34: =E35/(OEM!E40/OEM!E39) -> 1586.3484 | F34: =AWM!D74 -> 53.896274 | G34: =Haver!N44 -> 116.23333 | H34: =UK_HAVER!E46 -> 48.806511 | I34: =reconstruct_levels_ch!D34 -> 22.669605 | J34: =AWM!C74 -> 7.4535992 | K34: =Haver!H44 -> 6.75 | L34: =UK_HAVER!D46 -> 8.6333333 | M34: =M35/(OEM_aux!B40/OEM_aux!B39) -> 8.215301 | N34: =Haver!J44 -> 0.81052822 | O34: =1/UK_HAVER!F46 -> 0.5563695 | P34: =1/ '[2]Exchange rate'!$C39 -> 0.010377788 | R34: =Haver!R44 -> 15.736667 | S34: =Mater_Q!B35 -> 6.319
A35: 32295 | B35: =AWM!B75 -> 1812194.3 | C35: =Haver!D45 -> 2372.7 | D35: =UK_HAVER!C47 -> 365209 | E35: =E36/(OEM!E41/OEM!E40) -> 1628.4838 | F35: =AWM!D75 -> 54.28582 | G35: =Haver!N45 -> 117.56667 | H35: =UK_HAVER!E47 -> 49.226184 | I35: =reconstruct_levels_ch!D35 -> 23.91408 | J35: =AWM!C75 -> 7.2598364 | K35: =Haver!H45 -> 7.4375 | L35: =UK_HAVER!D47 -> 7.9533333 | M35: =M36/(OEM_aux!B41/OEM_aux!B40) -> 8.215301 | N35: =Haver!J45 -> 0.82118886 | O35: =1/UK_HAVER!F47 -> 0.54303557 | P35: =1/ '[2]Exchange rate'!$C40 -> 0.010308164 | R35: =Haver!R45 -> 16.15 | S35: =Mater_Q!B36 -> 6.4906667
A36: 32387 | B36: =AWM!B76 -> 1834640.2 | C36: =Haver!D46 -> 2386.6 | D36: =UK_HAVER!C48 -> 369774 | E36: =E37/(OEM!E42/OEM!E41) -> 1662.1782 | F36: =AWM!D76 -> 54.701298 | G36: =Haver!N46 -> 119 | H36: =UK_HAVER!E48 -> 49.862458 | I36: =reconstruct_levels_ch!D36 -> 26.066443 | J36: =AWM!C76 -> 7.9743925 | K36: =Haver!H46 -> 8.125 | L36: =UK_HAVER!D48 -> 10.89 | M36: =M37/(OEM_aux!B42/OEM_aux!B41) -> 8.6812937 | N36: =Haver!J46 -> 0.89768756 | O36: =1/UK_HAVER!F48 -> 0.5899009 | P36: =1/ '[2]Exchange rate'!$C41 -> 0.0098432947 | R36: =Haver!R46 -> 14.326667 | S36: =Mater_Q!B37 -> 6.7166667
A37: 32478 | B37: =AWM!B77 -> 1851607.8 | C37: =Haver!D47 -> 2418.4 | D37: =UK_HAVER!C49 -> 372752 | E37: =E38/(OEM!E43/OEM!E42) -> 1695.8015 | F37: =AWM!D77 -> 55.123779 | G37: =Haver!N47 -> 120.3 | H37: =UK_HAVER!E49 -> 50.533578 | I37: =reconstruct_levels_ch!D37 -> 27.756886 | J37: =AWM!C77 -> 8.4754225 | K37: =Haver!H47 -> 8.6875 | L37: =UK_HAVER!D49 -> 12.273333 | M37: =M38/(OEM_aux!B43/OEM_aux!B42) -> 9.6132828 | N37: =Haver!J47 -> 0.85469355 | O37: =1/UK_HAVER!F49 -> 0.5583369 | P37: =1/ '[2]Exchange rate'!$C42 -> 0.0099897805 | R37: =Haver!R47 -> 13.58 | S37: =Mater_Q!B38 -> 6.4266667
A38: 32568 | B38: =AWM!B78 -> 1873357.3 | C38: =Haver!D48 -> 2442.9 | D38: =UK_HAVER!C50 -> 374612 | E38: =E39/(OEM!E44/OEM!E43) -> 1656.5506 | F38: =AWM!D78 -> 55.831041 | G38: =Haver!N48 -> 121.66667 | H38: =UK_HAVER!E50 -> 51.259161 | I38: =reconstruct_levels_ch!D38 -> 29.027599 | J38: =AWM!C78 -> 9.5159466 | K38: =Haver!H48 -> 9.75 | L38: =UK_HAVER!D50 -> 12.88 | M38: =M39/(OEM_aux!B44/OEM_aux!B43) -> 11.63259 | N38: =Haver!J48 -> 0.88794175 | O38: =1/UK_HAVER!F50 -> 0.57246446 | P38: =1/ '[2]Exchange rate'!$C43 -> 0.0097782871 | R38: =Haver!R48 -> 17.586667 | S38: =Mater_Q!B39 -> 6.8013333
A39: 32660 | B39: =AWM!B79 -> 1891166.5 | C39: =Haver!D49 -> 2461.6 | D39: =UK_HAVER!C51 -> 376951 | E39: =E40/(OEM!E45/OEM!E44) -> 1697.6319 | F39: =AWM!D79 -> 56.474651 | G39: =Haver!N49 -> 123.63333 | H39: =UK_HAVER!E51 -> 51.840861 | I39: =reconstruct_levels_ch!D39 -> 29.809874 | J39: =AWM!C79 -> 9.6913451 | K39: =Haver!H49 -> 9.5625 | L39: =UK_HAVER!D51 -> 13.223333 | M39: =M40/(OEM_aux!B45/OEM_aux!B44) -> 12.642242 | N39: =Haver!J49 -> 0.93001916 | O39: =1/UK_HAVER!F51 -> 0.61418774 | P39: =1/ '[2]Exchange rate'!$C44 -> 0.0094009613 | R39: =Haver!R49 -> 18.873333 | S39: =Mater_Q!B40 -> 6.864
... A41: 32843 | B41: =AWM!B81 -> 1922300 | C41: =Haver!D51 -> 2484.7 | D41: =UK_HAVER!C53 -> 377508 | E41: =E42/(OEM!E47/OEM!E46) -> 1768.0902 | F41: =AWM!D81 -> 57.387609 | G41: =Haver!N51 -> 125.86667 | H41: =UK_HAVER!E53 -> 53.331518 | I41: =reconstruct_levels_ch!D41 -> 29.838444 | J41: =AWM!C81 -> 11.071902 | K41: =Haver!H51 -> 8.25 | L41: =UK_HAVER!D53 -> 14.81 | M41: =M42/(OEM_aux!B47/OEM_aux!B46) -> 12.642242 | N41: =Haver!J51 -> 0.88523255 | O41: =1/UK_HAVER!F53 -> 0.63071586 | P41: =1/ '[2]Exchange rate'!$C46 -> 0.0093827466 | R41: =Haver!R51 -> 19.16 | S41: =Mater_Q!B42 -> 7.1713333
A42: 32933 | B42: =AWM!B82 -> 1948361 | C42: =Haver!D52 -> 2511.9 | D42: =UK_HAVER!C54 -> 379458 | E42: =E43/(OEM!E48/OEM!E47) -> 1719.28 | F42: =AWM!D82 -> 58.106758 | G42: =Haver!N52 -> 128.03333 | H42: =UK_HAVER!E54 -> 54.222591 | I42: =reconstruct_levels_ch!D42 -> 30.307396 | J42: =AWM!C82 -> 11.225662 | K42: =Haver!H52 -> 8.25 | L42: =UK_HAVER!D54 -> 14.88 | M42: =M43/(OEM_aux!B48/OEM_aux!B47) -> 12.098583 | N42: =Haver!J52 -> 0.82923782 | O42: =1/UK_HAVER!F54 -> 0.60340319 | P42: =1/ '[2]Exchange rate'!$C47 -> 0.010850804 | Q42: =Haver!Q52 -> 22.223333 | R42: =Haver!R52 -> 19.816667 | S42: =Mater_Q!B43 -> 8.242
A43: 33025 | B43: =AWM!B83 -> 1957258.2 | C43: =Haver!D53 -> 2521 | D43: =UK_HAVER!C55 -> 381997 | E43: =E44/(OEM!E49/OEM!E48) -> 1762.4389 | F43: =AWM!D83 -> 58.605874 | G43: =Haver!N53 -> 129.3 | H43: =UK_HAVER!E55 -> 55.277047 | I43: =reconstruct_levels_ch!D43 -> 30.474693 | J43: =AWM!C83 -> 10.618018 | K43: =Haver!H53 -> 8.25 | L43: =UK_HAVER!D55 -> 14.88 | M43: =M44/(OEM_aux!B49/OEM_aux!B48) -> 11.011265 | N43: =Haver!J53 -> 0.81816992 | O43: =1/UK_HAVER!F55 -> 0.59702681 | P43: =1/ '[2]Exchange rate'!$C48 -> 0.010728673 | Q43: =Haver!Q53 -> 18.773333 | R43: =Haver!R53 -> 16.02 | S43: =Mater_Q!B44 -> 8.692
A44: 33117 | B44: =AWM!B84 -> 1975410.8 | C44: =Haver!D54 -> 2522.7 | D44: =UK_HAVER!C56 -> 377831 | E44: =E45/(OEM!E50/OEM!E49) -> 1799.5153 | F44: =AWM!D84 -> 59.14673 | G44: =Haver!N54 -> 131.53333 | H44: =UK_HAVER!E56 -> 56.360326 | I44: =reconstruct_levels_ch!D44 -> 30.564372 | J44: =AWM!C84 -> 10.536337 | K44: =Haver!H54 -> 8 | L44: =UK_HAVER!D56 -> 14.88 | M44: =M45/(OEM_aux!B50/OEM_aux!B49) -> 10.389939 | N44: =Haver!J54 -> 0.77100804 | O44: =1/UK_HAVER!F56 -> 0.53662463 | P44: =1/ '[2]Exchange rate'!$C49 -> 0.011008941 | Q44: =Haver!Q54 -> 25.226667 | R44: =Haver!R54 -> 26.413333 | S44: =Mater_Q!B45 -> 8.8013333
A45: 33208 | B45: =AWM!B85 -> 1986588.9 | C45: =Haver!D55 -> 2499.7 | D45: =UK_HAVER!C57 -> 375916 | E45: =E46/(OEM!E51/OEM!E50) -> 1842.8076 | F45: =AWM!D85 -> 59.910068 | G45: =Haver!N55 -> 133.76667 | H45: =UK_HAVER!E57 -> 57.530704 | I45: =reconstruct_levels_ch!D45 -> 30.932343 | J45: =AWM!C85 -> 11.046291 | K45: =Haver!H55 -> 7 | L45: =UK_HAVER!D57 -> 13.95 | M45: =M46/(OEM_aux!B51/OEM_aux!B50) -> 10.079277 | N45: =Haver!J55 -> 0.73163594 | O45: =1/UK_HAVER!F57 -> 0.51442975 | P45: =1/ '[2]Exchange rate'!$C50 -> 0.011837787 | Q45: =Haver!Q55 -> 25.96 | R45: =Haver!R55 -> 32.453333 | S45: =Mater_Q!B46 -> 8.9216667
A46: 33298 | B46: =AWM!B86 -> 2000317.5 | C46: =Haver!D56 -> 2488 | D46: =UK_HAVER!C58 -> 374060 | E46: =E47/(OEM!E52/OEM!E51) -> 1872.5031 | F46: =AWM!D86 -> 60.523557 | G46: =Haver!N56 -> 134.76667 | H46: =UK_HAVER!E58 -> 57.987863 | I46: =reconstruct_levels_ch!D46 -> 30.959507 | J46: =AWM!C86 -> 11.096523 | K46: =Haver!H56 -> 6 | L46: =UK_HAVER!D58 -> 13.386667 | M46: =M47/(OEM_aux!B52/OEM_aux!B51) -> 10.079277 | N46: =Haver!J56 -> 0.74585677 | O46: =1/UK_HAVER!F58 -> 0.52446636 | P46: =1/ '[2]Exchange rate'!$C51 -> 0.012126357 | Q46: =Haver!Q56 -> 22.256667 | R46: =Haver!R56 -> 20.73 | S46: =Mater_Q!B47 -> 8.5543333
A47: 33390 | B47: =AWM!B87 -> 2006259.2 | C47: =Haver!D57 -> 2507.4 | D47: =UK_HAVER!C59 -> 373608 | E47: =E48/(OEM!E53/OEM!E52) -> 1924.9098 | F47: =AWM!D87 -> 61.119654 | G47: =Haver!N57 -> 135.56667 | H47: =UK_HAVER!E59 -> 59.907205 | I47: =reconstruct_levels_ch!D47 -> 31.397207 | J47: =AWM!C87 -> 10.461558 | K47: =Haver!H57 -> 5.75 | L47: =UK_HAVER!D59 -> 11.736667 | M47: =M48/(OEM_aux!B53/OEM_aux!B52) -> 9.1472889 | N47: =Haver!J57 -> 0.84243869 | O47: =1/UK_HAVER!F59 -> 0.58557152 | P47: =1/ '[2]Exchange rate'!$C52 -> 0.01169763 | Q47: =Haver!Q57 -> 17.146667 | R47: =Haver!R57 -> 18.846667 | S47: =Mater_Q!B48 -> 8.338
A48: 33482 | B48: =AWM!B88 -> 2005704.9 | C48: =Haver!D58 -> 2520.1 | D48: =UK_HAVER!C60 -> 372878 | E48: =E49/(OEM!E54/OEM!E53) -> 1971.9698 | F48: =AWM!D88 -> 61.901554 | G48: =Haver!N58 -> 136.6 | H48: =UK_HAVER!E60 -> 60.795959 | I48: =reconstruct_levels_ch!D48 -> 31.9606 | J48: =AWM!C88 -> 10.505996 | K48: =Haver!H58 -> 5.25 | L48: =UK_HAVER!D60 -> 10.79 | M48: =M49/(OEM_aux!B54/OEM_aux!B53) -> 9.1472889 | N48: =Haver!J58 -> 0.84912469 | O48: =1/UK_HAVER!F60 -> 0.59266283 | P48: =1/ '[2]Exchange rate'!$C53 -> 0.011618287 | Q48: =Haver!Q58 -> 16.643333 | R48: =Haver!R58 -> 19.89 | S48: =Mater_Q!B49 -> 8.5153333
A49: 33573 | B49: =AWM!B89 -> 2024779.2 | C49: =Haver!D59 -> 2528.8 | D49: =UK_HAVER!C61 -> 373357 | E49: =E50/(OEM!E55/OEM!E54) -> 2025.5522 | F49: =AWM!D89 -> 62.399618 | G49: =Haver!N59 -> 137.73333 | H49: =UK_HAVER!E61 -> 61.532523 | I49: =reconstruct_levels_ch!D49 -> 32.338296 | J49: =AWM!C89 -> 10.732215 | K49: =Haver!H59 -> 4 | L49: =UK_HAVER!D61 -> 10.38 | M49: =M50/(OEM_aux!B55/OEM_aux!B54) -> 9.1472889 | N49: =Haver!J59 -> 0.79580874 | O49: =1/UK_HAVER!F61 -> 0.56286234 | P49: =1/ '[2]Exchange rate'!$C54 -> 0.011728164 | Q49: =Haver!Q59 -> 17.493333 | R49: =Haver!R59 -> 20.576667 | S49: =Mater_Q!B50 -> 8.2596667
A50: 33664 | B50: =AWM!B90 -> 2055344.3 | C50: =Haver!D60 -> 2559.1 | D50: =UK_HAVER!C62 -> 373317 | E50: =reconstruct_levels_ch!I50 -> 2111.33 | F50: =AWM!D90 -> 63.063435 | G50: =Haver!N60 -> 138.66667 | H50: =UK_HAVER!E62 -> 62.041971 | I50: =reconstruct_levels_ch!D50 -> 32.654094 | J50: =AWM!C90 -> 10.849247 | K50: =Haver!H60 -> 4 | L50: =UK_HAVER!D62 -> 10.38 | M50: =M51/(OEM_aux!B56/OEM_aux!B55) -> 9.1472889 | N50: =Haver!J60 -> 0.79200184 | O50: =1/UK_HAVER!F62 -> 0.56490792 | P50: =1/ '[2]Exchange rate'!$C55 -> 0.011518829 | Q50: =Haver!Q60 -> 17.56 | R50: =Haver!R60 -> 17.946667 | S50: =Mater_Q!B51 -> 7.9203333
A51: 33756 | B51: =AWM!B91 -> 2039655.4 | C51: =Haver!D61 -> 2586.9 | D51: =UK_HAVER!C63 -> 372751 | E51: =reconstruct_levels_ch!I51 -> 2211.7393 | F51: =AWM!D91 -> 63.705368 | G51: =Haver!N61 -> 139.73333 | H51: =UK_HAVER!E63 -> 62.458775 | I51: =reconstruct_levels_ch!D51 -> 33.150093 | J51: =AWM!C91 -> 10.979088 | K51: =Haver!H61 -> 3.75 | L51: =UK_HAVER!D63 -> 10.053333 | M51: =M52/(OEM_aux!B57/OEM_aux!B56) -> 9.1472889 | N51: =Haver!J61 -> 0.78663765 | O51: =1/UK_HAVER!F63 -> 0.55338301 | P51: =1/ '[2]Exchange rate'!$C56 -> 0.011469403 | Q51: =Haver!Q61 -> 15.613333 | R51: =Haver!R61 -> 19.99 | S51: =Mater_Q!B52 -> 8.008
A52: 33848 | B52: =AWM!B92 -> 2033943.7 | C52: =Haver!D62 -> 2612.4 | D52: =UK_HAVER!C64 -> 374537 | E52: =reconstruct_levels_ch!I52 -> 2293.0167 | F52: =AWM!D92 -> 64.012141 | G52: =Haver!N62 -> 140.8 | H52: =UK_HAVER!E64 -> 62.701767 | I52: =reconstruct_levels_ch!D52 -> 33.901803 | J52: =AWM!C92 -> 11.928409 | K52: =Haver!H62 -> 3 | L52: =UK_HAVER!D64 -> 9.7733333 | M52: =M53/(OEM_aux!B58/OEM_aux!B57) -> 9.1472889 | N52: =Haver!J62 -> 0.72128909 | O52: =1/UK_HAVER!F64 -> 0.52561497 | P52: =1/ '[2]Exchange rate'!$C57 -> 0.011480417 | Q52: =Haver!Q62 -> 13.906667 | R52: =Haver!R62 -> 20.083333 | S52: =Mater_Q!B53 -> 7.924
A53: 33939 | B53: =AWM!B93 -> 2029876.7 | C53: =Haver!D63 -> 2639.7 | D53: =UK_HAVER!C65 -> 377418 | E53: =reconstruct_levels_ch!I53 -> 2354.785 | F53: =AWM!D93 -> 64.439827 | G53: =Haver!N63 -> 142.03333 | H53: =UK_HAVER!E65 -> 63.204533 | I53: =reconstruct_levels_ch!D53 -> 35.034773 | J53: =AWM!C93 -> 11.451664 | K53: =Haver!H63 -> 3 | L53: =UK_HAVER!D65 -> 7.52 | M53: =M54/(OEM_aux!B59/OEM_aux!B58) -> 9.1472889 | N53: =Haver!J63 -> 0.78883846 | O53: =1/UK_HAVER!F65 -> 0.63415562 | P53: =1/ '[2]Exchange rate'!$C58 -> 0.0112514 | Q53: =Haver!Q63 -> 14.75 | R53: =Haver!R63 -> 19.203333 | S53: =Mater_Q!B54 -> 7.3296667
A54: 34029 | B54: =AWM!B94 -> 2016046 | C54: =Haver!D64 -> 2644.1 | D54: =UK_HAVER!C66 -> 379370 | E54: =reconstruct_levels_ch!I54 -> 2430.7798 | F54: =AWM!D94 -> 65.221968 | G54: =Haver!N64 -> 143.06667 | H54: =UK_HAVER!E66 -> 63.522509 | I54: =reconstruct_levels_ch!D54 -> 36.255181 | J54: =AWM!C94 -> 10.706123 | K54: =Haver!H64 -> 3 | L54: =UK_HAVER!D66 -> 6.1466667 | M54: =M55/(OEM_aux!B60/OEM_aux!B59) -> 9.1472889 | N54: =Haver!J64 -> 0.83958592 | O54: =1/UK_HAVER!F66 -> 0.67663577 | P54: =1/ '[2]Exchange rate'!$C59 -> 0.011015279 | Q54: =Haver!Q64 -> 13.246667 | R54: =Haver!R64 -> 18.216667 | S54: =Mater_Q!B55 -> 6.908
A55: 34121 | B55: =AWM!B95 -> 2017541.5 | C55: =Haver!D65 -> 2659.5 | D55: =UK_HAVER!C67 -> 381045 | E55: =reconstruct_levels_ch!I55 -> 2512.367 | F55: =AWM!D95 -> 65.815692 | G55: =Haver!N65 -> 144.1 | H55: =UK_HAVER!E67 -> 64.066811 | I55: =reconstruct_levels_ch!D55 -> 37.821678 | J55: =AWM!C95 -> 9.0912239 | K55: =Haver!H65 -> 3 | L55: =UK_HAVER!D67 -> 5.88 | M55: =M56/(OEM_aux!B61/OEM_aux!B60) -> 9.6219115 | N55: =Haver!J65 -> 0.82798821 | O55: =1/UK_HAVER!F67 -> 0.65208886 | P55: =1/ '[2]Exchange rate'!$C60 -> 0.010898052 | Q55: =Haver!Q65 -> 12.99 | R55: =Haver!R65 -> 18.276667 | S55: =Mater_Q!B56 -> 6.75
A56: 34213 | B56: =AWM!B96 -> 2025906.4 | C56: =Haver!D66 -> 2672.2 | D56: =UK_HAVER!C68 -> 384524 | E56: =reconstruct_levels_ch!I56 -> 2593.7092 | F56: =AWM!D96 -> 66.241832 | G56: =Haver!N66 -> 144.76667 | H56: =UK_HAVER!E68 -> 64.483439 | I56: =reconstruct_levels_ch!D56 -> 39.33785 | J56: =AWM!C96 -> 8.1200999 | K56: =Haver!H66 -> 3 | L56: =UK_HAVER!D68 -> 5.88 | M56: =M57/(OEM_aux!B62/OEM_aux!B61) -> 11.951882 | N56: =Haver!J66 -> 0.86936363 | O56: =1/UK_HAVER!F68 -> 0.66493783 | P56: =1/ '[2]Exchange rate'!$C61 -> 0.010701416 | Q56: =Haver!Q66 -> 12.12 | R56: =Haver!R66 -> 16.496667 | S56: =Mater_Q!B57 -> 6.374
A57: 34304 | B57: =AWM!B97 -> 2031211.4 | C57: =Haver!D67 -> 2708.5 | D57: =UK_HAVER!C69 -> 387143 | E57: =reconstruct_levels_ch!I57 -> 2688.2727 | F57: =AWM!D97 -> 66.57439 | G57: =Haver!N67 -> 145.96667 | H57: =UK_HAVER!E69 -> 64.73546 | I57: =reconstruct_levels_ch!D57 -> 41.054907 | J57: =AWM!C97 -> 7.4121286 | K57: =Haver!H67 -> 3 | L57: =UK_HAVER!D69 -> 5.6666667 | M57: =M58/(OEM_aux!B63/OEM_aux!B62) -> 12.17625 | N57: =Haver!J67 -> 0.87678023 | O57: =1/UK_HAVER!F69 -> 0.67048096 | P57: =1/ '[2]Exchange rate'!$C62 -> 0.010468023 | Q57: =Haver!Q67 -> 12.44 | R57: =Haver!R67 -> 15.18 | S57: =Mater_Q!B58 -> 5.8773333
A58: 34394 | B58: =AWM!B98 -> 2050033 | C58: =Haver!D68 -> 2734.8 | D58: =UK_HAVER!C70 -> 391026 | E58: =reconstruct_levels_ch!I58 -> 2768.1913 | F58: =AWM!D98 -> 67.214227 | G58: =Haver!N68 -> 146.7 | H58: =UK_HAVER!E70 -> 65.056755 | I58: =reconstruct_levels_ch!D58 -> 44.231991 | J58: =AWM!C98 -> 6.84 | K58: =Haver!H68 -> 3.5 | L58: =UK_HAVER!D70 -> 5.2333333 | M58: =M59/(OEM_aux!B64/OEM_aux!B63) -> 12.17625 | N58: =Haver!J68 -> 0.88924722 | O58: =1/UK_HAVER!F70 -> 0.67213335 | P58: =1/ '[2]Exchange rate'!$C63 -> 0.01531467 | Q58: =Haver!Q68 -> 13.383333 | R58: =Haver!R68 -> 13.97 | S58: =Mater_Q!B59 -> 6.012
A59: 34486 | B59: =AWM!B99 -> 2062801.1 | C59: =Haver!D69 -> 2771.9 | D59: =UK_HAVER!C71 -> 394588 | E59: =reconstruct_levels_ch!I59 -> 2854.1825 | F59: =AWM!D99 -> 67.689886 | G59: =Haver!N69 -> 147.53333 | H59: =UK_HAVER!E71 -> 65.360131 | I59: =reconstruct_levels_ch!D59 -> 46.17608 | J59: =AWM!C99 -> 6.37 | K59: =Haver!H69 -> 4.25 | L59: =UK_HAVER!D71 -> 5.13 | M59: =M60/(OEM_aux!B65/OEM_aux!B64) -> 12.17625 | N59: =Haver!J69 -> 0.86030633 | O59: =1/UK_HAVER!F71 -> 0.66479048 | P59: =1/ '[2]Exchange rate'!$C64 -> 0.015129616 | Q59: =Haver!Q69 -> 14.593333 | R59: =Haver!R69 -> 16.06 | S59: =Mater_Q!B60 -> 6.7046667
A60: 34578 | B60: =AWM!B100 -> 2076692.6 | C60: =Haver!D70 -> 2788.1 | D60: =UK_HAVER!C72 -> 398566 | E60: =reconstruct_levels_ch!I60 -> 2939.2535 | F60: =AWM!D100 -> 68.067811 | G60: =Haver!N70 -> 148.9 | H60: =UK_HAVER!E72 -> 65.631457 | I60: =reconstruct_levels_ch!D60 -> 49.403226 | J60: =AWM!C100 -> 6.3833333 | K60: =Haver!H70 -> 4.75 | L60: =UK_HAVER!D72 -> 5.2433333 | M60: =M61/(OEM_aux!B66/OEM_aux!B65) -> 12.17625 | N60: =Haver!J70 -> 0.81511993 | O60: =1/UK_HAVER!F72 -> 0.64446831 | P60: =1/ '[2]Exchange rate'!$C65 -> 0.015139576 | Q60: =Haver!Q70 -> 12.533333 | R60: =Haver!R70 -> 16.796667 | S60: =Mater_Q!B61 -> 7.175
A61: 34669 | B61: =AWM!B101 -> 2093169.7 | C61: =Haver!D71 -> 2820 | D61: =UK_HAVER!C73 -> 400279 | E61: =reconstruct_levels_ch!I61 -> 3009.9947 | F61: =AWM!D101 -> 68.353966 | G61: =Haver!N71 -> 149.76667 | H61: =UK_HAVER!E73 -> 65.856796 | I61: =reconstruct_levels_ch!D61 -> 52.108145 | J61: =AWM!C101 -> 6.5066667 | K61: =Haver!H71 -> 5.5 | L61: =UK_HAVER!D73 -> 5.7633333 | M61: =M62/(OEM_aux!B67/OEM_aux!B66) -> 12.17625 | N61: =Haver!J71 -> 0.8063519 | O61: =1/UK_HAVER!F73 -> 0.63100772 | P61: =1/ '[2]Exchange rate'!$C66 -> 0.014974014 | Q61: =Haver!Q71 -> 15.27 | R61: =Haver!R71 -> 16.536667 | S61: =Mater_Q!B62 -> 7.507
A62: 34759 | B62: =Haver!C72 -> 2113963.1 | C62: =Haver!D72 -> 2830 | D62: =UK_HAVER!C74 -> 402390 | E62: =reconstruct_levels_ch!I62 -> 3089.5176 | F62: =AWM!D102 -> 68.946385 | G62: =Haver!N72 -> 150.86667 | H62: =UK_HAVER!E74 -> 66.590862 | I62: =reconstruct_levels_ch!D62 -> 54.14977 | J62: =AWM!C102 -> 6.9433333 | K62: =Haver!H72 -> 6 | L62: =UK_HAVER!D74 -> 6.4533333 | M62: =M63/(OEM_aux!B68/OEM_aux!B67) -> 12.17625 | N62: =Haver!J72 -> 0.78604611 | O62: =1/UK_HAVER!F74 -> 0.63200472 | P62: =1/ '[2]Exchange rate'!$C67 -> 0.014718664 | Q62: =Haver!Q72 -> 11.97 | R62: =Haver!R72 -> 16.89 | S62: =Mater_Q!B63 -> 7.41
A63: 34851 | B63: =Haver!C73 -> 2130670.8 | C63: =Haver!D73 -> 2838.4 | D63: =UK_HAVER!C75 -> 403259 | E63: =reconstruct_levels_ch!I63 -> 3175.1782 | F63: =AWM!D103 -> 69.515173 | G63: =Haver!N73 -> 152.1 | H63: =UK_HAVER!E75 -> 66.959746 | I63: =reconstruct_levels_ch!D63 -> 55.367596 | J63: =AWM!C103 -> 7.1366667 | K63: =Haver!H73 -> 6 | L63: =UK_HAVER!D75 -> 6.63 | M63: =M64/(OEM_aux!B69/OEM_aux!B68) -> 12.17625 | N63: =Haver!J73 -> 0.75103079 | O63: =1/UK_HAVER!F75 -> 0.62637018 | P63: =1/ '[2]Exchange rate'!$C68 -> 0.0150304 | Q63: =Haver!Q73 -> 12.203333 | R63: =Haver!R73 -> 18.103333 | S63: =Mater_Q!B64 -> 6.872
A64: 34943 | B64: =Haver!C74 -> 2135994.9 | C64: =Haver!D74 -> 2862.6 | D64: =UK_HAVER!C76 -> 407795 | E64: =reconstruct_levels_ch!I64 -> 3257.4316 | F64: =AWM!D104 -> 69.80123 | G64: =Haver!N74 -> 152.86667 | H64: =UK_HAVER!E76 -> 67.413472 | I64: =reconstruct_levels_ch!D64 -> 56.706597 | J64: =AWM!C104 -> 6.6933333 | K64: =Haver!H74 -> 5.75 | L64: =UK_HAVER!D76 -> 6.63 | M64: =M65/(OEM_aux!B70/OEM_aux!B69) -> 13.574235 | N64: =Haver!J74 -> 0.76180416 | O64: =1/UK_HAVER!F76 -> 0.63545859 | P64: =1/ '[2]Exchange rate'!$C69 -> 0.014617534 | Q64: =Haver!Q74 -> 12.456667 | R64: =Haver!R74 -> 16.216667 | S64: =Mater_Q!B65 -> 6.6836667
A65: 35034 | B65: =Haver!C75 -> 2140682.9 | C65: =Haver!D75 -> 2882 | D65: =UK_HAVER!C77 -> 409132 | E65: =reconstruct_levels_ch!I65 -> 3328.1633 | F65: =AWM!D105 -> 70.08396 | G65: =Haver!N75 -> 153.7 | H65: =UK_HAVER!E77 -> 67.765392 | I65: =reconstruct_levels_ch!D65 -> 57.863203 | J65: =AWM!C105 -> 6.5066667 | K65: =Haver!H75 -> 5.5 | L65: =UK_HAVER!D77 -> 6.58 | M65: =M66/(OEM_aux!B71/OEM_aux!B70) -> 13.574235 | N65: =Haver!J75 -> 0.75943984 | O65: =1/UK_HAVER!F77 -> 0.64090239 | P65: =1/ '[2]Exchange rate'!$C70 -> 0.01432754 | Q65: =Haver!Q75 -> 12.86 | R65: =Haver!R75 -> 16.966667 | S65: =Mater_Q!B66 -> 6.312
A66: 35125 | B66: =Haver!C76 -> 2144754.9 | C66: =Haver!D76 -> 2903.6 | D66: =UK_HAVER!C78 -> 412022 | E66: =reconstruct_levels_ch!I66 -> 3417.8521 | F66: =AWM!D106 -> 70.669379 | G66: =Haver!N76 -> 155.06667 | H66: =UK_HAVER!E78 -> 68.338576 | I66: =reconstruct_levels_ch!D66 -> 59.149029 | J66: =AWM!C106 -> 5.63 | K66: =Haver!H76 -> 5.25 | L66: =UK_HAVER!D78 -> 6.1233333 | M66: =M67/(OEM_aux!B72/OEM_aux!B71) -> 13.574235 | N66: =Haver!J76 -> 0.77684384 | O66: =1/UK_HAVER!F78 -> 0.65332433 | P66: =1/ '[2]Exchange rate'!$C71 -> 0.014060837 | Q66: =Haver!Q76 -> 15.42 | R66: =Haver!R76 -> 18.566667 | S66: =Mater_Q!B67 -> 6.176
A67: 35217 | B67: =Haver!C77 -> 2161523.5 | C67: =Haver!D77 -> 2952 | D67: =UK_HAVER!C79 -> 413325 | E67: =reconstruct_levels_ch!I67 -> 3481.203 | F67: =AWM!D107 -> 71.228188 | G67: =Haver!N77 -> 156.4 | H67: =UK_HAVER!E79 -> 68.593587 | I67: =reconstruct_levels_ch!D67 -> 60.49556 | J67: =AWM!C107 -> 5.1366667 | K67: =Haver!H77 -> 5.25 | L67: =UK_HAVER!D79 -> 5.87 | M67: =M68/(OEM_aux!B73/OEM_aux!B72) -> 12.642242 | N67: =Haver!J77 -> 0.79713033 | O67: =1/UK_HAVER!F79 -> 0.65605318 | P67: =1/ '[2]Exchange rate'!$C72 -> 0.013911271 | Q67: =Haver!Q77 -> 16.376667 | R67: =Haver!R77 -> 19.503333 | S67: =Mater_Q!B68 -> 6.4693333
A68: 35309 | B68: =Haver!C78 -> 2171466.1 | C68: =Haver!D78 -> 2978.5 | D68: =UK_HAVER!C80 -> 417019 | E68: =reconstruct_levels_ch!I68 -> 3571.6034 | F68: =AWM!D108 -> 71.298039 | G68: =Haver!N78 -> 157.3 | H68: =UK_HAVER!E80 -> 68.955417 | I68: =reconstruct_levels_ch!D68 -> 61.23109 | J68: =AWM!C108 -> 5 | K68: =Haver!H78 -> 5.25 | L68: =UK_HAVER!D80 -> 5.69 | M68: =M69/(OEM_aux!B74/OEM_aux!B73) -> 11.680053 | N68: =Haver!J78 -> 0.78473225 | O68: =1/UK_HAVER!F80 -> 0.64347304 | P68: =1/ '[2]Exchange rate'!$C73 -> 0.013803177 | Q68: =Haver!Q78 -> 16.773333 | R68: =Haver!R78 -> 20.903333 | S68: =Mater_Q!B69 -> 6.3383333
A69: 35400 | B69: =Haver!C79 -> 2183386.6 | C69: =Haver!D79 -> 3009.5 | D69: =UK_HAVER!C81 -> 422639 | E69: =reconstruct_levels_ch!I69 -> 3661.9278 | F69: =AWM!D109 -> 71.55416 | G69: =Haver!N79 -> 158.66667 | H69: =UK_HAVER!E81 -> 69.368193 | I69: =reconstruct_levels_ch!D69 -> 61.818942 | J69: =AWM!C109 -> 4.5866667 | K69: =Haver!H79 -> 5.25 | L69: =UK_HAVER!D81 -> 5.8633333 | M69: =M70/(OEM_aux!B75/OEM_aux!B74) -> 11.011265 | N69: =Haver!J79 -> 0.79248513 | O69: =1/UK_HAVER!F81 -> 0.61068702 | P69: =1/ '[2]Exchange rate'!$C74 -> 0.013616654 | Q69: =Haver!Q79 -> 17.213333 | R69: =Haver!R79 -> 23.566667 | S69: =Mater_Q!B70 -> 5.883
A70: 35490 | B70: =Haver!C80 -> 2189616.2 | C70: =Haver!D80 -> 3028.9 | D70: =UK_HAVER!C82 -> 429418 | E70: =reconstruct_levels_ch!I70 -> 3756.6571 | F70: =Haver!M80 -> 72.8 | G70: =Haver!N80 -> 159.63333 | H70: =UK_HAVER!E82 -> 69.600154 | I70: =reconstruct_levels_ch!D70 -> 62.133351 | J70: =AWM!C110 -> 4.44 | K70: =Haver!H80 -> 5.5 | L70: =UK_HAVER!D82 -> 5.94 | M70: =M71/(OEM_aux!B76/OEM_aux!B75) -> 11.011265 | N70: =Haver!J80 -> 0.84944206 | O70: =1/UK_HAVER!F82 -> 0.61303308 | P70: =1/ '[2]Exchange rate'!$C75 -> 0.013101223 | Q70: =Haver!Q80 -> 19.926667 | R70: =Haver!R80 -> 21.173333 | S70: =Mater_Q!B71 -> 5.7106667
A71: 35582 | B71: =Haver!C81 -> 2215960.3 | C71: =Haver!D81 -> 3079.3 | D71: =UK_HAVER!C83 -> 434199 | E71: =reconstruct_levels_ch!I71 -> 3838.9084 | F71: =Haver!M81 -> 72.846667 | G71: =Haver!N81 -> 160 | H71: =UK_HAVER!E83 -> 69.751646 | I71: =reconstruct_levels_ch!D71 -> 62.408369 | J71: =AWM!C111 -> 4.3266667 | K71: =Haver!H81 -> 5.5 | L71: =UK_HAVER!D83 -> 6.2033333 | M71: =M72/(OEM_aux!B77/OEM_aux!B76) -> 11.011265 | N71: =Haver!J81 -> 0.87438574 | O71: =1/UK_HAVER!F83 -> 0.61144627 | P71: =1/ '[2]Exchange rate'!$C76 -> 0.012934649 | Q71: =Haver!Q81 -> 19.923333 | R71: =Haver!R81 -> 18.053333 | S71: =Mater_Q!B72 -> 5.8163333
A72: 35674 | B72: =Haver!C82 -> 2233286.1 | C72: =Haver!D82 -> 3117.8 | D72: =UK_HAVER!C84 -> 438100 | E72: =reconstruct_levels_ch!I72 -> 3892.5646 | F72: =Haver!M82 -> 73.186667 | G72: =Haver!N82 -> 160.8 | H72: =UK_HAVER!E84 -> 70.300066 | I72: =reconstruct_levels_ch!D72 -> 62.56652 | J72: =AWM!C112 -> 4.3233333 | K72: =Haver!H82 -> 5.5 | L72: =UK_HAVER!D84 -> 6.8733333 | M72: =M73/(OEM_aux!B78/OEM_aux!B77) -> 11.011265 | N72: =Haver!J82 -> 0.91531505 | O72: =1/UK_HAVER!F84 -> 0.61548562 | P72: =1/ '[2]Exchange rate'!$C77 -> 0.012601132 | Q72: =Haver!Q82 -> 22.473333 | R72: =Haver!R82 -> 18.506667 | S72: =Mater_Q!B73 -> 5.608
A73: 35765 | B73: =Haver!C83 -> 2256628.9 | C73: =Haver!D83 -> 3144.4 | D73: =UK_HAVER!C85 -> 444540 | E73: =reconstruct_levels_ch!I73 -> 3971.1883 | F73: =Haver!M83 -> 73.483333 | G73: =Haver!N83 -> 161.66667 | H73: =UK_HAVER!E85 -> 70.597745 | I73: =reconstruct_levels_ch!D73 -> 62.354013 | J73: =AWM!C113 -> 4.4333333 | K73: =Haver!H83 -> 5.5 | L73: =UK_HAVER!D85 -> 7.1533333 | M73: =M74/(OEM_aux!B79/OEM_aux!B78) -> 9.5787643 | N73: =Haver!J83 -> 0.88987236 | O73: =1/UK_HAVER!F85 -> 0.60221616 | P73: =1/ '[2]Exchange rate'!$C78 -> 0.011957434 | Q73: =Haver!Q83 -> 27.453333 | R73: =Haver!R83 -> 18.74 | S73: =Mater_Q!B74 -> 5.484
A74: 35855 | B74: =Haver!C84 -> 2273109.1 | C74: =Haver!D84 -> 3175.9 | D74: =UK_HAVER!C86 -> 447712 | E74: =reconstruct_levels_ch!I74 -> 4020.6888 | F74: =Haver!M84 -> 73.556667 | G74: =Haver!N84 -> 162 | H74: =UK_HAVER!E86 -> 70.745328 | I74: =reconstruct_levels_ch!D74 -> 62.208009 | J74: =AWM!C114 -> 4.2033333 | K74: =Haver!H84 -> 5.5 | L74: =UK_HAVER!D86 -> 7.25 | M74: =M75/(OEM_aux!B80/OEM_aux!B79) -> 9.0782519 | N74: =Haver!J84 -> 0.92010428 | O74: =1/UK_HAVER!F86 -> 0.60757033 | P74: =1/ '[2]Exchange rate'!$C79 -> 0.011128422 | Q74: =Haver!Q84 -> 21.343333 | R74: =Haver!R84 -> 14.12 | S74: =Mater_Q!B75 -> 5.0063333
A75: 35947 | B75: =Haver!C85 -> 2281728 | C75: =Haver!D85 -> 3205.3 | D75: =UK_HAVER!C87 -> 450292 | E75: =reconstruct_levels_ch!I75 -> 4111.3444 | F75: =Haver!M85 -> 73.796667 | G75: =Haver!N85 -> 162.53333 | H75: =UK_HAVER!E87 -> 71.032659 | I75: =reconstruct_levels_ch!D75 -> 62.009474 | J75: =AWM!C115 -> 4.0566667 | K75: =Haver!H85 -> 5.5 | L75: =UK_HAVER!D87 -> 7.3233333 | M75: =M76/(OEM_aux!B81/OEM_aux!B80) -> 8.215301 | N75: =Haver!J85 -> 0.90867237 | O75: =1/UK_HAVER!F87 -> 0.60472898 | P75: =1/ '[2]Exchange rate'!$C80 -> 0.011182488 | Q75: =Haver!Q85 -> 21.52 | R75: =Haver!R85 -> 13.366667 | S75: =Mater_Q!B76 -> 4.8866667
A76: 36039 | B76: =Haver!C86 -> 2293780.3 | C76: =Haver!D86 -> 3245.7 | D76: =UK_HAVER!C88 -> 451005 | E76: =reconstruct_levels_ch!I76 -> 4207.6148 | F76: =Haver!M86 -> 73.96 | G76: =Haver!N86 -> 163.36667 | H76: =UK_HAVER!E88 -> 71.265754 | I76: =reconstruct_levels_ch!D76 -> 61.697076 | J76: =AWM!C116 -> 3.9366667 | K76: =Haver!H86 -> 5.25 | L76: =UK_HAVER!D88 -> 7.5 | M76: =M77/(OEM_aux!B82/OEM_aux!B81) -> 6.9338177 | N76: =Haver!J86 -> 0.89466778 | O76: =1/UK_HAVER!F88 -> 0.60481432 | P76: =1/ '[2]Exchange rate'!$C81 -> 0.01100406 | Q76: =Haver!Q86 -> 29.906667 | R76: =Haver!R86 -> 12.443333 | S76: =Mater_Q!B77 -> 4.384
A77: 36130 | B77: =Haver!C87 -> 2300668.1 | C77: =Haver!D87 -> 3297.9 | D77: =UK_HAVER!C89 -> 453937 | E77: =reconstruct_levels_ch!I77 -> 4339.7107 | F77: =Haver!M87 -> 74.043333 | G77: =Haver!N87 -> 164.13333 | H77: =UK_HAVER!E89 -> 71.576093 | I77: =reconstruct_levels_ch!D77 -> 61.591004 | J77: =AWM!C117 -> 3.6233333 | K77: =Haver!H87 -> 4.75 | L77: =UK_HAVER!D89 -> 6.85 | M77: =M78/(OEM_aux!B83/OEM_aux!B82) -> 6.7396522 | N77: =Haver!J87 -> 0.84978614 | O77: =1/UK_HAVER!F89 -> 0.59686051 | P77: =1/ '[2]Exchange rate'!$C82 -> 0.01141751 | Q77: =Haver!Q87 -> 29.436667 | R77: =Haver!R87 -> 11.186667 | S77: =Mater_Q!B78 -> 4.001
A78: 36220 | B78: =Haver!C88 -> 2323517.7 | C78: =Haver!D88 -> 3328.9 | D78: =UK_HAVER!C90 -> 457044 | E78: =reconstruct_levels_ch!I78 -> 4369.0555 | F78: =Haver!M88 -> 74.11 | G78: =Haver!N88 -> 164.73333 | H78: =UK_HAVER!E90 -> 71.859035 | I78: =reconstruct_levels_ch!D78 -> 61.238438 | J78: =AWM!C118 -> 3.0907319 | K78: =Haver!H88 -> 4.75 | L78: =UK_HAVER!D90 -> 5.7066667 | M78: =M79/(OEM_aux!B84/OEM_aux!B83) -> 6.2348268 | N78: =Haver!J88 -> 0.89024972 | O78: =1/UK_HAVER!F90 -> 0.61240737 | P78: =1/ '[2]Exchange rate'!$C83 -> 0.011225769 | Q78: =Haver!Q88 -> 27.39 | R78: =Haver!R88 -> 11.296667 | S78: =Mater_Q!B79 -> 3.856
A79: 36312 | B79: =Haver!C89 -> 2334547 | C79: =Haver!D89 -> 3356.7 | D79: =UK_HAVER!C91 -> 458710 | E79: =reconstruct_levels_ch!I79 -> 4436.3785 | F79: =Haver!M89 -> 74.493333 | G79: =Haver!N89 -> 165.96667 | H79: =UK_HAVER!E91 -> 72.071161 | I79: =reconstruct_levels_ch!D79 -> 60.786748 | J79: =AWM!C119 -> 2.6340296 | K79: =Haver!H89 -> 5 | L79: =UK_HAVER!D91 -> 5.2066667 | M79: =M80/(OEM_aux!B85/OEM_aux!B84) -> 6.0751798 | N79: =Haver!J89 -> 0.946072 | O79: =1/UK_HAVER!F91 -> 0.62249704 | P79: =1/ '[2]Exchange rate'!$C84 -> 0.011009781 | Q79: =Haver!Q89 -> 24.436667 | R79: =Haver!R89 -> 15.46 | S79: =Mater_Q!B80 -> 4.0833333
A80: 36404 | B80: =Haver!C90 -> 2365082.6 | C80: =Haver!D90 -> 3401.2 | D80: =UK_HAVER!C92 -> 466387 | E80: =reconstruct_levels_ch!I80 -> 4535.7708 | F80: =Haver!M90 -> 74.783333 | G80: =Haver!N90 -> 167.2 | H80: =UK_HAVER!E92 -> 72.163213 | I80: =reconstruct_levels_ch!D80 -> 61.012665 | J80: =AWM!C120 -> 2.6993939 | K80: =Haver!H90 -> 5.25 | L80: =UK_HAVER!D92 -> 5.0633333 | M80: =M81/(OEM_aux!B86/OEM_aux!B85) -> 5.5358359 | N80: =Haver!J90 -> 0.95368281 | O80: =1/UK_HAVER!F92 -> 0.62427168 | P80: =1/ '[2]Exchange rate'!$C85 -> 0.011068404 | Q80: =Haver!Q90 -> 23.303333 | R80: =Haver!R90 -> 20.613333 | S80: =Mater_Q!B81 -> 4.8666667
A81: 36495 | B81: =Haver!C91 -> 2389876.2 | C81: =Haver!D91 -> 3457 | D81: =UK_HAVER!C93 -> 473892 | E81: =reconstruct_levels_ch!I81 -> 4651.005 | F81: =Haver!M91 -> 75.163333 | G81: =Haver!N91 -> 168.43333 | H81: =UK_HAVER!E93 -> 72.368947 | I81: =reconstruct_levels_ch!D81 -> 61.020708 | J81: =AWM!C121 -> 3.429798 | K81: =Haver!H91 -> 5.5 | L81: =UK_HAVER!D93 -> 5.4066667 | M81: =M82/(OEM_aux!B87/OEM_aux!B86) -> 5.5358359 | N81: =Haver!J91 -> 0.96293657 | O81: =1/UK_HAVER!F93 -> 0.61338404 | P81: =1/ '[2]Exchange rate'!$C86 -> 0.011171089 | Q81: =Haver!Q91 -> 22.626667 | R81: =Haver!R91 -> 24.016667 | S81: =Mater_Q!B82 -> 5.1753333
... A136: 41518 | B136: =Haver!C146 -> 2783857.4 | C136: =Haver!D146 -> 4465.1 | D136: =UK_HAVER!C148 -> 588076 | E136: =reconstruct_levels_ch!I136 -> 17120.278 | F136: =Haver!M146 -> 99.586667 | G136: =Haver!N146 -> 233.3 | H136: =UK_HAVER!E148 -> 98.735154 | I136: =reconstruct_levels_ch!D136 -> 84.182332 | J136: =AWM!C176 -> 0.22351217 | K136: =Haver!H146 -> 0.25 | L136: =UK_HAVER!D148 -> 0.5 | M136: =M137/(OEM_aux!B142/OEM_aux!B141) -> 5.73 | N136: =Haver!J146 -> 0.75495382 | O136: =1/UK_HAVER!F148 -> 0.64420537 | P136: =1/ '[2]Exchange rate'!$C141 -> 0.0087681226 | Q136: =Haver!Q146 -> 14.29 | R136: =Haver!R146 -> 110.27 | S136: =Mater_Q!B137 -> 1.786
A137: 41609 | B137: =Haver!C147 -> 2789570.1 | C137: =Haver!D147 -> 4504 | D137: =UK_HAVER!C149 -> 591954 | E137: =reconstruct_levels_ch!I137 -> 17430.418 | F137: =Haver!M147 -> 99.55 | G137: =Haver!N147 -> 234.16267 | H137: =UK_HAVER!E149 -> 99.188278 | I137: =reconstruct_levels_ch!D137 -> 84.821629 | J137: =AWM!C177 -> 0.24090235 | K137: =Haver!H147 -> 0.25 | L137: =UK_HAVER!D149 -> 0.5 | M137: =Haver!I147 -> 5.73 | N137: =Haver!J147 -> 0.73472759 | O137: =1/UK_HAVER!F149 -> 0.61752537 | P137: =1/ '[2]Exchange rate'!$C142 -> 0.0087951598 | Q137: =Haver!Q147 -> 14.173333 | R137: =Haver!R147 -> 109.21 | S137: =Mater_Q!B138 -> 1.7933333
A138: 41699 | B138: =Haver!C148 -> 2802623.5 | C138: =Haver!D148 -> 4488.5 | D138: =UK_HAVER!C150 -> 596696 | E138: =reconstruct_levels_ch!I138 -> 17751.541 | F138: =Haver!M148 -> 99.806667 | G138: =Haver!N148 -> 235.621 | H138: =UK_HAVER!E150 -> 99.609605 | I138: =reconstruct_levels_ch!D138 -> 85.182102 | J138: =AWM!C178 -> 0.2951596 | K138: =Haver!H148 -> 0.25 | L138: =UK_HAVER!D150 -> 0.5 | M138: =Haver!I148 -> 5.76 | N138: =Haver!J148 -> 0.73008244 | O138: =1/UK_HAVER!F150 -> 0.60420527 | P138: =1/ '[2]Exchange rate'!$C143 -> 0.0087022962 | Q138: =Haver!Q148 -> 14.85 | R138: =Haver!R148 -> 108.16667 | S138: =Mater_Q!B139 -> 1.682
A139: 41791 | B139: =Haver!C149 -> 2809125 | C139: =Haver!D149 -> 4546.5 | D139: =UK_HAVER!C151 -> 602310 | E139: =reconstruct_levels_ch!I139 -> 18063.657 | F139: =Haver!M149 -> 99.806667 | G139: =Haver!N149 -> 236.87233 | H139: =UK_HAVER!E151 -> 99.996833 | I139: =reconstruct_levels_ch!D139 -> 85.491093 | J139: =AWM!C179 -> 0.29858333 | K139: =Haver!H149 -> 0.25 | L139: =UK_HAVER!D151 -> 0.5 | M139: =Haver!I149 -> 5.76 | N139: =Haver!J149 -> 0.72927013 | O139: =1/UK_HAVER!F151 -> 0.59408293 | P139: =1/ '[2]Exchange rate'!$C144 -> 0.0089759758 | Q139: =Haver!Q149 -> 12.74 | R139: =Haver!R149 -> 109.7 | S139: =Mater_Q!B140 -> 1.427
A140: 41883 | B140: =Haver!C150 -> 2822836.8 | C140: =Haver!D150 -> 4601.7 | D140: =UK_HAVER!C152 -> 607213 | E140: =reconstruct_levels_ch!I140 -> 18378.242 | F140: =Haver!M150 -> 99.9 | G140: =Haver!N150 -> 237.47833 | H140: =UK_HAVER!E152 -> 100.13528 | I140: =reconstruct_levels_ch!D140 -> 85.811396 | J140: =AWM!C180 -> 0.16456861 | K140: =Haver!H150 -> 0.25 | L140: =UK_HAVER!D152 -> 0.5 | M140: =Haver!I150 -> 5.76 | N140: =Haver!J150 -> 0.75459112 | O140: =1/UK_HAVER!F152 -> 0.59932875 | P140: =1/ '[2]Exchange rate'!$C145 -> 0.0087669926 | Q140: =Haver!Q150 -> 13.086667 | R140: =Haver!R150 -> 101.82333 | S140: =Mater_Q!B141 -> 1.0696667
A141: 41974 | B141: =Haver!C151 -> 2833377.6 | C141: =Haver!D151 -> 4625 | D141: =UK_HAVER!C153 -> 611220 | E141: =reconstruct_levels_ch!I141 -> 18709.453 | F141: =Haver!M151 -> 99.73 | G141: =Haver!N151 -> 236.88833 | H141: =UK_HAVER!E153 -> 100.06536 | I141: =reconstruct_levels_ch!D141 -> 86.047808 | J141: =AWM!C181 -> 0.081471153 | K141: =Haver!H151 -> 0.25 | L141: =UK_HAVER!D153 -> 0.5 | M141: =Haver!I151 -> 5.51 | N141: =Haver!J151 -> 0.80050656 | O141: =1/UK_HAVER!F153 -> 0.63172524 | P141: =1/ '[2]Exchange rate'!$C146 -> 0.0083050339 | Q141: =Haver!Q151 -> 15.92 | R141: =Haver!R151 -> 76.403333 | S141: =Mater_Q!B142 -> 0.77
A142: 42064 | B142: =Haver!C152 -> 2854919.4 | C142: =Haver!D152 -> 4666.7 | D142: =UK_HAVER!C154 -> 613076 | E142: =reconstruct_levels_ch!I142 -> 19016.348 | F142: =Haver!M152 -> 99.676667 | G142: =Haver!N152 -> 235.355 | H142: =UK_HAVER!E154 -> 99.739894 | I142: =reconstruct_levels_ch!D142 -> 86.228898 | J142: =AWM!C182 -> 0.046016162 | K142: =Haver!H152 -> 0.25 | L142: =UK_HAVER!D154 -> 0.5 | M142: =Haver!I152 -> 5.3 | N142: =Haver!J152 -> 0.88734661 | O142: =1/UK_HAVER!F154 -> 0.66037113 | P142: =1/ '[2]Exchange rate'!$C147 -> 0.0080023111 | Q142: =Haver!Q152 -> 16.61 | R142: =Haver!R152 -> 53.916667 | S142: =Mater_Q!B143 -> 0.35266667
A143: 42156 | B143: =Haver!C153 -> 2866851.2 | C143: =Haver!D153 -> 4695.6 | D143: =UK_HAVER!C155 -> 615875 | E143: =reconstruct_levels_ch!I143 -> 19344.715 | F143: =Haver!M153 -> 100.16333 | G143: =Haver!N153 -> 236.96 | H143: =UK_HAVER!E155 -> 99.982273 | I143: =reconstruct_levels_ch!D143 -> 86.709483 | J143: =AWM!C183 -> -0.0065258373 | K143: =Haver!H153 -> 0.25 | L143: =UK_HAVER!D155 -> 0.5 | M143: =Haver!I153 -> 4.8 | N143: =Haver!J153 -> 0.90519364 | O143: =1/UK_HAVER!F155 -> 0.65217391 | P143: =1/ '[2]Exchange rate'!$C148 -> 0.0079188351 | Q143: =Haver!Q153 -> 13.723333 | R143: =Haver!R153 -> 61.693333 | S143: =Mater_Q!B144 -> 0.526
A144: 42248 | B144: =Haver!C154 -> 2879444.1 | C144: =Haver!D154 -> 4714.4 | D144: =UK_HAVER!C156 -> 618263 | E144: =reconstruct_levels_ch!I144 -> 19666.947 | F144: =Haver!M154 -> 100.09333 | G144: =Haver!N154 -> 237.855 | H144: =UK_HAVER!E156 -> 100.13597 | I144: =reconstruct_levels_ch!D144 -> 87.312204 | J144: =AWM!C184 -> -0.027817084 | K144: =Haver!H154 -> 0.25 | L144: =UK_HAVER!D156 -> 0.5 | M144: =Haver!I154 -> 4.55 | N144: =Haver!J154 -> 0.89938815 | O144: =1/UK_HAVER!F156 -> 0.64549445 | P144: =1/ '[2]Exchange rate'!$C149 -> 0.0078424545 | Q144: =Haver!Q154 -> 19.386667 | R144: =Haver!R154 -> 50.233333 | S144: =Mater_Q!B145 -> 0.699
A145: 42339 | B145: =Haver!C155 -> 2893722.8 | C145: =Haver!D155 -> 4723.1 | D145: =UK_HAVER!C157 -> 621968 | E145: =reconstruct_levels_ch!I145 -> 19999.251 | F145: =Haver!M155 -> 100.07 | G145: =Haver!N155 -> 237.837 | H145: =UK_HAVER!E157 -> 100.15569 | I145: =reconstruct_levels_ch!D145 -> 87.275011 | J145: =AWM!C185 -> -0.089176046 | K145: =Haver!H155 -> 0.5 | L145: =UK_HAVER!D157 -> 0.5 | M145: =Haver!I155 -> 4.3 | N145: =Haver!J155 -> 0.91329011 | O145: =1/UK_HAVER!F157 -> 0.65907992 | P145: =1/ '[2]Exchange rate'!$C150 -> 0.0078677154 | Q145: =Haver!Q155 -> 17.01 | R145: =Haver!R155 -> 43.57 | S145: =Mater_Q!B146 -> 0.56366667
A146: 42430 | B146: =Haver!C156 -> 2907682.4 | C146: =Haver!D156 -> 4750.4 | D146: =UK_HAVER!C158 -> 625099 | E146: =reconstruct_levels_ch!I146 -> 20315.049 | F146: =Haver!M156 -> 99.723333 | G146: =Haver!N156 -> 237.68933 | H146: =UK_HAVER!E158 -> 100.10444 | I146: =reconstruct_levels_ch!D146 -> 88.105457 | J146: =AWM!C186 -> -0.18608175 | K146: =Haver!H156 -> 0.5 | L146: =UK_HAVER!D158 -> 0.5 | M146: =Haver!I156 -> 4.3 | N146: =Haver!J156 -> 0.90765324 | O146: =1/UK_HAVER!F158 -> 0.69879574 | P146: =1/ '[2]Exchange rate'!$C151 -> 0.0080178059 | Q146: =Haver!Q156 -> 20.696667 | R146: =Haver!R156 -> 33.693333 | S146: =Mater_Q!B147 -> 0.31633333
A147: 42522 | B147: =Haver!C157 -> 2912999.2 | C147: =Haver!D157 -> 4765.7 | D147: =UK_HAVER!C159 -> 629697 | E147: =reconstruct_levels_ch!I147 -> 20639.87 | F147: =Haver!M157 -> 100.07 | G147: =Haver!N157 -> 239.59033 | H147: =UK_HAVER!E159 -> 100.31689 | I147: =reconstruct_levels_ch!D147 -> 88.52213 | J147: =AWM!C187 -> -0.2580938 | K147: =Haver!H157 -> 0.5 | L147: =UK_HAVER!D159 -> 0.5 | M147: =Haver!I157 -> 4.3 | N147: =Haver!J157 -> 0.88549933 | O147: =1/UK_HAVER!F159 -> 0.69702602 | P147: =1/ '[2]Exchange rate'!$C152 -> 0.0082492392 | Q147: =Haver!Q157 -> 15.64 | R147: =Haver!R157 -> 45.523333 | S147: =Mater_Q!B148 -> 0.116
A148: 42614 | B148: =Haver!C158 -> 2927132 | C148: =Haver!D158 -> 4799.5 | D148: =UK_HAVER!C160 -> 632477 | E148: =reconstruct_levels_ch!I148 -> 20967.758 | F148: =Haver!M158 -> 100.35 | G148: =Haver!N158 -> 240.60733 | H148: =UK_HAVER!E160 -> 100.81174 | I148: =reconstruct_levels_ch!D148 -> 88.758845 | J148: =AWM!C188 -> -0.29812585 | K148: =Haver!H158 -> 0.5 | L148: =UK_HAVER!D160 -> 0.34333333 | M148: =Haver!I158 -> 4.3 | N148: =Haver!J158 -> 0.89572693 | O148: =1/UK_HAVER!F160 -> 0.76190476 | P148: =1/ '[2]Exchange rate'!$C153 -> 0.0084844628 | Q148: =Haver!Q158 -> 13.26 | R148: =Haver!R158 -> 45.786667 | S148: =Mater_Q!B149 -> -0.069666667
... A177: 45261 | B177: =Haver!C187 -> 3240423.9 | C177: =Haver!D187 -> 5758.5 | D177: =UK_HAVER!C189 -> 685628 | E177: =reconstruct_levels_ch!I177 -> 31014.232 | F177: =Haver!M187 -> 124.2 | G177: =Haver!N187 -> 308.195 | H177: =UK_HAVER!E189 -> 131.8589 | I177: =reconstruct_levels_ch!D177 -> 99.889939 | J177: =AWM!C217 -> 3.957456 | K177: =Haver!H187 -> 5.5 | L177: =UK_HAVER!D189 -> 5.25 | M177: =Haver!I187 -> 3.45 | N177: =Haver!J187 -> 0.9295457 | O177: =1/UK_HAVER!F189 -> 0.80495854 | P177: =1/ '[2]Exchange rate'!$C182 -> 0.0079534754 | Q177: =Haver!Q187 -> 15.21 | R177: =Haver!R187 -> 83.776667 | S177: =Mater_Q!B178 -> 2.5263333
A178: 45352 | B178: =Haver!C188 -> 3251227.4 | C178: =Haver!D188 -> 5770.5 | D178: =UK_HAVER!C190 -> 690605 | E178: =reconstruct_levels_ch!I178 -> 31424.029 | F178: =Haver!M188 -> 125.09 | G178: =Haver!N188 -> 311.00333 | H178: =UK_HAVER!E190 -> 132.94596 | I178: =reconstruct_levels_ch!D178 -> 100.10105 | J178: =Haver!G188 -> 4 | K178: =Haver!H188 -> 5.5 | L178: =UK_HAVER!D190 -> 5.25 | M178: =Haver!I188 -> 3.45 | N178: =Haver!J188 -> 0.92103506 | O178: =1/UK_HAVER!F190 -> 0.78856061 | P178: =1/ '[2]Exchange rate'!$C183 -> 0.007920447 | Q178: =Haver!Q188 -> 13.72 | R178: =Haver!R188 -> 83.003333 | S178: =Mater_Q!B179 -> 2.3163333
A179: 45444 | B179: =Haver!C189 -> 3258283.2 | C179: =Haver!D189 -> 5821.6 | D179: =UK_HAVER!C191 -> 694810 | E179: =reconstruct_levels_ch!I179 -> 31824.914 | F179: =Haver!M189 -> 125.74333 | G179: =Haver!N189 -> 313.08067 | H179: =UK_HAVER!E191 -> 133.22908 | I179: =reconstruct_levels_ch!D179 -> 100.11339 | J179: =Haver!G189 -> 3.75 | K179: =Haver!H189 -> 5.5 | L179: =UK_HAVER!D191 -> 5.25 | M179: =Haver!I189 -> 3.45 | N179: =Haver!J189 -> 0.92882161 | O179: =1/UK_HAVER!F191 -> 0.79220471 | P179: =1/ '[2]Exchange rate'!$C184 -> 0.0078417842 | Q179: =Haver!Q189 -> 13.956667 | R179: =Haver!R189 -> 84.646667 | S179: =Mater_Q!B180 -> 2.4976667
A180: 45536 | B180: =Haver!C190 -> 3272596.7 | C180: =Haver!D190 -> 5869.7 | D180: =UK_HAVER!C192 -> 696183 | E180: =reconstruct_levels_ch!I180 -> 32139.743 | F180: =Haver!M190 -> 126.34667 | G180: =Haver!N190 -> 314.121 | H180: =UK_HAVER!E192 -> 134.10633 | I180: =reconstruct_levels_ch!D180 -> 100.39574 | J180: =Haver!G190 -> 3.5 | K180: =Haver!H190 -> 5 | L180: =UK_HAVER!D192 -> 5.0833333 | M180: =Haver!I190 -> 3.35 | N180: =Haver!J190 -> 0.91013149 | O180: =1/UK_HAVER!F192 -> 0.76856074 | P180: =1/ '[2]Exchange rate'!$C185 -> 0.0078691641 | Q180: =Haver!Q190 -> 17.113333 | R180: =Haver!R190 -> 79.803333 | S180: =Mater_Q!B181 -> 2.2966667
A181: 45627 | B181: =Haver!C191 -> 3284793.9 | C181: =Haver!D191 -> 5896.6 | D181: =UK_HAVER!C193 -> 699177 | E181: =reconstruct_levels_ch!I181 -> 32695.37 | F181: =Haver!M191 -> 126.98 | G181: =Haver!N191 -> 316.58767 | H181: =UK_HAVER!E193 -> 135.1886 | I181: =reconstruct_levels_ch!D181 -> 100.09547 | J181: =Haver!G191 -> 3 | K181: =Haver!H191 -> 4.5 | L181: =UK_HAVER!D193 -> 4.85 | M181: =Haver!I191 -> 3.1 | N181: =Haver!J191 -> 0.93711227 | O181: =1/UK_HAVER!F193 -> 0.78068075 | P181: =1/ '[2]Exchange rate'!$C186 -> 0.007754607 | Q181: =Haver!Q191 -> 17.283333 | R181: =Haver!R191 -> 74.62 | S181: =Mater_Q!B182 -> 2.2606667
A182: 45717 | B182: =Haver!C192 -> 3306314.3 | C182: =Haver!D192 -> 5887.1 | D182: =UK_HAVER!C194 -> 703218 | E182: =reconstruct_levels_ch!I182 -> 33070.305 | F182: =Haver!M192 -> 127.99 | G182: =Haver!N192 -> 319.475 | H182: =UK_HAVER!E194 -> 136.62337 | I182: =reconstruct_levels_ch!D182 -> 100.02851 | J182: =Haver!G192 -> 2.5 | K182: =Haver!H192 -> 4.5 | L182: =UK_HAVER!D194 -> 4.5966667 | M182: =Haver!I192 -> 3.1 | N182: =Haver!J192 -> 0.95017775 | O182: =1/UK_HAVER!F194 -> 0.79346187 | P182: =1/ '[2]Exchange rate'!$C187 -> 0.0077554971 | Q182: =Haver!Q192 -> 18.523333 | R182: =Haver!R192 -> 75.833333 | S182: =Mater_Q!B183 -> 2.58
A183: 45809 | B183: =Haver!C193 -> 3310395 | C183: =Haver!D193 -> 5942.8 | D183: =UK_HAVER!C195 -> 704206 | E183: =reconstruct_levels_ch!I183 -> 33501.031 | F183: =Haver!M193 -> 128.26667 | G183: =Haver!N193 -> 320.78567 | H183: =UK_HAVER!E195 -> 137.86657 | I183: =reconstruct_levels_ch!D183 -> 100.13057 | J183: =Haver!G193 -> 2 | K183: =Haver!H193 -> 4.5 | L183: =UK_HAVER!D195 -> 4.35 | M183: =Haver!I193 -> 3 | N183: =Haver!J193 -> 0.88214045 | O183: =1/UK_HAVER!F195 -> 0.74852167 | P183: =1/ '[2]Exchange rate'!$C188 -> 0.0080429558 | Q183: =Haver!Q193 -> 23.61 | R183: =Haver!R193 -> 68.006667 | S183: =Mater_Q!B184 -> 2.554
...

Sheet Haver
C1: EZGDP | D1: USGDP | E1: CHGDP | F1: CHGDP | G1: EZRR | H1: USRR | I1: CHRR | J1: USDEUR | K1: USDCNY | L1: EURCNY | M1: EZCPI | N1: USCPI | O1: CHCPI | P1: CHCPI | Q1: VIX | R1: poil brent | S1: poil wti | T1: EZ10Y
A2: 19801 *Q | B2: .excel_last | C2: J025GDPT@EUDATA | D2: S111NGPC@G10 | E2: H924NGPC@EMERGE | F2: SA(DIFF%(H924NGPC@EMERGE)) | G2: N023RTAR@G10 | H2: N111RTAU@G10 | I2: N924RTAR@EMERGE | J2: 1/(X111EXR@EUDATA) | K2: FXCHI@USECON | L2: X924EXR@EUDATA | M2: P023SH@EUDATA | N2: S111PC@G10 | O2: H924PC@EMERGE | P2: SA(DIFF%(H924PC@EMERGE)) | Q2: SPVIX@USECON | R2: N112POIL@G10 | S2: N111POIL@G10 | T2: I023R@EUDATA
A3: .DESC | C3: EA21: Gross Domestic Product (SWDA, Mil.Ch.2020.EUR) | D3: U.S.: Gross Domestic Product (SA, Bil.Chn.2017$) | E3: China: Gross Domestic Product (SA, Bil.2020.Yuan) | F3: China: Gross Domestic Product (SA, 2020.Yuan) | G3: Euro Area 11-21: Deposit Rate (EOP, %) | H3: U.S.: Federal Open Market Committee: Fed Funds Target Rate: Upper Limit (EOP, %) | I3: China: Loan Prime Rate: 1 Year (EOP, %) | J3: Euro Exchange Rate: United States Dollar (Avg, USD/EUR) | K3: Foreign Exchange Rate: People's Republic of China (Yuan/US$) | L3: Euro Exchange Rate: Chinese Yuan Renminbi (Avg, Yuan/Euro) | M3: EA11-20: HICP DISC(SWDA, 2015=100) | N3: U.S.: Consumer Price Index (SA, 1982-84=100) | O3: China: Consumer Price Index (SA, 2025=100) | P3: China: Consumer Price Index (SA, 2025=100) | Q3: CBOE Market Volatility Index: VIX (Index) | R3: European Brent Spot Price FOB ($/Barrel) | S3: U.S.: Spot Oil Price: West Texas Intermediate [Prior'82=Posted Price] ($/Barrel) | T3: Euro Area 11-21: Long Term Government Bond Yield: Rolling 12 Month Average (%)
A4: .T1 | C4: Q1-1995 | D4: Q1-1947 | E4: Q1-1992 | F4: Q1-1992 | G4: Q1-1999 <- Jan-1999 | H4: Q3-1982 <- Sep-1982 | I4: Q4-2013 <- Oct-2013 | J4: Q1-1971 <- Jan-1971 | K4: Q1-1970 <- Jan-1970 | L4: Q1-2000 <- Jan-2000 | M4: Q1-1997 <- Jan-1997 | N4: Q1-1947 <- Jan-1947 | O4: Q1-1984 <- Jan-1984 | P4: Q1-1984 <- Jan-1984 | Q4: Q1-1990 <- Jan-1990 | R4: Q2-1986 <- Jun-1986 | S4: Q1-1946 <- Jan-1946 | T4: Q4-1991 <- Nov-1991
A5: .TN | C5: Q1-2026 | D5: Q1-2026 | E5: Q1-2026 | F5: Q1-2026 | G5: Q1-2026 <- May-2026 | H5: Q1-2026 <- May-2026 | I5: Q1-2026 <- May-2026 | J5: Q1-2026 <- May-2026 | K5: Q1-2026 <- May-2026 | L5: Q1-2026 <- May-2026 | M5: Q4-2025 <- Dec-2025 | N5: Q1-2026 <- Apr-2026 | O5: Q1-2026 <- Apr-2026 | P5: Q1-2026 <- Apr-2026 | Q5: Q1-2026 <- May-2026 | R5: Q1-2026 <- May-2026 | S5: Q1-2026 <- May-2026 | T5: Q1-2026 <- Apr-2026
A6: .SOURCE | C6: Eurostat | D6: BEA | E6: CNBS | F6: CNBS | G6: ECB | H6: FRB | I6: PBoC | J6: ECB | K6: FRB | L6: ECB | M6: DISC | N6: BLS | O6: CNBS/H | P6: CNBS/H | Q6: CBOE | R6: EIA | S6: WSJ | T6: ECB
A7: .LSOURCE | C7: Statistical Office of the European Communities | D7: Bureau of Economic Analysis | E7: China National Bureau of Statistics | F7: China National Bureau of Statistics | G7: European Central Bank | H7: Federal Reserve Board | I7: People's Bank of China | J7: European Central Bank | K7: Federal Reserve Board | L7: European Central Bank | M7: Discontinued | N7: Bureau of Labor Statistics | O7: China National Bureau of Statistics/Haver Analytics | P7: China National Bureau of Statistics/Haver Analytics | Q7: Chicago Board Options Exchange | R7: Energy Information Administration | S7: Wall Street Journal | T7: European Central Bank
A8: .AGG | C8: Sum | D8: Sum | E8: Sum | F8: Sum | G8: End of Period | H8: End of Period | I8: End of Period | J8: Average | K8: Average | L8: Average | M8: Average | N8: Average | O8: Average | P8: Average | Q8: Average | R8: Average | S8: Average | T8: Average
A9: .FRQ | C9: Quarterly | D9: Quarterly | E9: Quarterly | F9: Quarterly | G9: Quarterly <- Monthly | H9: Quarterly <- Monthly | I9: Quarterly <- Monthly | J9: Quarterly <- Monthly | K9: Quarterly <- Monthly | L9: Quarterly <- Monthly | M9: Quarterly <- Monthly | N9: Quarterly <- Monthly | O9: Quarterly <- Monthly | P9: Quarterly <- Monthly | Q9: Quarterly <- Monthly | R9: Quarterly <- Monthly | S9: Quarterly <- Monthly | T9: Quarterly <- Monthly
A10: .MAG | C10: 6 | D10: 9 | E10: 9 | F10: 0 <- 9 | G10: 0 | H10: 0 | I10: 0 | J10: 0 | K10: 0 | L10: 0 | M10: 0 | N10: 0 | O10: 0 | P10: 0 | Q10: 0 | R10: 0 | S10: 0 | T10: 0
A11: .GEO2 | C11: Not Defined | D11: Not Defined | E11: Not Defined | F11: Not Defined | G11: Not Defined | H11: Not Defined | I11: Not Defined | J11: 023 | K11: 111 | L11: 023 | M11: Not Defined | N11: Not Defined | O11: Not Defined | P11: Not Defined | Q11: Not Defined | R11: Not Defined | S11: Not Defined | T11: Not Defined
A12: 19801 | B12: 29311 | C12: #N/A | D12: 1835.4 | E12: #N/A | F12: #N/A | G12: #N/A | H12: #N/A | I12: #N/A | J12: 0.70891484 | K12: 1.5151333 | L12: #N/A | M12: #N/A | N12: 79.033333 | O12: #N/A | P12: #N/A | Q12: #N/A | R12: #N/A | S12: 35.833333 | T12: #N/A
A13: 19802 | B13: 29402 | C13: #N/A | D13: 1797.6 | E13: #N/A | F13: #N/A | G13: #N/A | H13: #N/A | I13: #N/A | J13: 0.71904683 | K13: 1.5008333 | L13: #N/A | M13: #N/A | N13: 81.7 | O13: #N/A | P13: #N/A | Q13: #N/A | R13: #N/A | S13: 39.5 | T13: #N/A
A14: 19803 | B14: 29494 | C14: #N/A | D14: 1795.4 | E14: #N/A | F14: #N/A | G14: #N/A | H14: #N/A | I14: #N/A | J14: 0.70283289 | K14: 1.4644 | L14: #N/A | M14: #N/A | N14: 83.233333 | O14: #N/A | P14: #N/A | Q14: #N/A | R14: #N/A | S14: 37.833333 | T14: #N/A
A15: 19804 | B15: 29586 | C15: #N/A | D15: 1828.9 | E15: #N/A | F15: #N/A | G15: #N/A | H15: #N/A | I15: #N/A | J15: 0.74632621 | K15: 1.5131667 | L15: #N/A | M15: #N/A | N15: 85.566667 | O15: #N/A | P15: #N/A | Q15: #N/A | R15: #N/A | S15: 36.333333 | T15: #N/A
A16: 19811 | B16: 29676 | C16: #N/A | D16: 1864.8 | E16: #N/A | F16: #N/A | G16: #N/A | H16: #N/A | I16: #N/A | J16: 0.81110895 | K16: 1.5987667 | L16: #N/A | M16: #N/A | N16: 87.933333 | O16: #N/A | P16: #N/A | Q16: #N/A | R16: #N/A | S16: 38 | T16: #N/A
A17: 19812 | B17: 29767 | C17: #N/A | D17: 1850.9 | E17: #N/A | F17: #N/A | G17: #N/A | H17: #N/A | I17: #N/A | J17: 0.89624206 | K17: 1.7178333 | L17: #N/A | M17: #N/A | N17: 89.766667 | O17: #N/A | P17: #N/A | Q17: #N/A | R17: #N/A | S17: 37.333333 | T17: #N/A
A18: 19813 | B18: 29859 | C18: #N/A | D18: 1873.1 | E18: #N/A | F18: #N/A | G18: #N/A | H18: #N/A | I18: #N/A | J18: 0.96849799 | K18: 1.7730667 | L18: #N/A | M18: #N/A | N18: 92.266667 | O18: #N/A | P18: #N/A | Q18: #N/A | R18: #N/A | S18: 36 | T18: #N/A
A19: 19814 | B19: 29951 | C19: #N/A | D19: 1852.7 | E19: #N/A | F19: #N/A | G19: #N/A | H19: #N/A | I19: #N/A | J19: 0.91801513 | K19: 1.7463333 | L19: #N/A | M19: #N/A | N19: 93.766667 | O19: #N/A | P19: #N/A | Q19: #N/A | R19: #N/A | S19: 35.333333 | T19: #N/A
A20: 19821 | B20: 30041 | C20: #N/A | D20: 1823.9 | E20: #N/A | F20: #N/A | G20: #N/A | H20: #N/A | I20: #N/A | J20: 0.96385852 | K20: 1.8114 | L20: #N/A | M20: #N/A | N20: 94.6 | O20: #N/A | P20: #N/A | Q20: #N/A | R20: #N/A | S20: 31.296667 | T20: #N/A
A21: 19822 | B21: 30132 | C21: #N/A | D21: 1832.2 | E21: #N/A | F21: #N/A | G21: #N/A | H21: #N/A | I21: #N/A | J21: 0.99683737 | K21: 1.8567333 | L21: #N/A | M21: #N/A | N21: 95.966667 | O21: #N/A | P21: #N/A | Q21: #N/A | R21: #N/A | S21: 34.816667 | T21: #N/A
A22: 19823 | B22: 30224 | C22: #N/A | D22: 1825.2 | E22: #N/A | F22: #N/A | G22: #N/A | H22: 10.25 | I22: #N/A | J22: 1.0519222 | K22: 1.9433 | L22: #N/A | M22: #N/A | N22: 97.633333 | O22: #N/A | P22: #N/A | Q22: #N/A | R22: #N/A | S22: 34.58 | T22: #N/A
A23: 19824 | B23: 30316 | C23: #N/A | D23: 1826 | E23: #N/A | F23: #N/A | G23: #N/A | H23: 8.5 | I23: #N/A | J23: 1.0711849 | K23: 1.9778 | L23: #N/A | M23: #N/A | N23: 97.933333 | O23: #N/A | P23: #N/A | Q23: #N/A | R23: #N/A | S23: 33.85 | T23: #N/A
A24: 19831 | B24: 30406 | C24: #N/A | D24: 1850 | E24: #N/A | F24: #N/A | G24: #N/A | H24: 8.625 | I24: #N/A | J24: 1.0548208 | K24: 1.9575 | L24: #N/A | M24: #N/A | N24: 98 | O24: #N/A | P24: #N/A | Q24: #N/A | R24: #N/A | S24: 29.653333 | T24: #N/A
A25: 19832 | B25: 30497 | C25: #N/A | D25: 1892.1 | E25: #N/A | F25: #N/A | G25: #N/A | H25: 9 | I25: #N/A | J25: 1.0964135 | K25: 1.9927333 | L25: #N/A | M25: #N/A | N25: 99.133333 | O25: #N/A | P25: #N/A | Q25: #N/A | R25: #N/A | S25: 30.536667 | T25: #N/A
A26: 19833 | B26: 30589 | C26: #N/A | D26: 1929.9 | E26: #N/A | F26: #N/A | G26: #N/A | H26: 9.375 | I26: #N/A | J26: 1.1613215 | K26: 1.9892 | L26: #N/A | M26: #N/A | N26: 100.1 | O26: #N/A | P26: #N/A | Q26: #N/A | R26: #N/A | S26: 31.56 | T26: #N/A
A27: 19834 | B27: 30681 | C27: #N/A | D27: 1970.2 | E27: #N/A | F27: #N/A | G27: #N/A | H27: 9.375 | I27: #N/A | J27: 1.1850185 | K27: 1.9841333 | L27: #N/A | M27: #N/A | N27: 101.1 | O27: #N/A | P27: #N/A | Q27: #N/A | R27: #N/A | S27: 29.83 | T27: #N/A
A28: 19841 | B28: 30772 | C28: #N/A | D28: 2008.7 | E28: #N/A | F28: #N/A | G28: #N/A | H28: 10.5 | I28: #N/A | J28: 1.2024318 | K28: 2.0588 | L28: #N/A | M28: #N/A | N28: 102.53333 | O28: 16.84 | P28: #N/A | Q28: #N/A | R28: #N/A | S28: 30.198667 | T28: #N/A
A29: 19842 | B29: 30863 | C29: #N/A | D29: 2043.4 | E29: #N/A | F29: #N/A | G29: #N/A | H29: 10.5 | I29: #N/A | J29: 1.2116977 | K29: 2.1657667 | L29: #N/A | M29: #N/A | N29: 103.5 | O29: 16.95 | P29: 0.0067228861 | Q29: #N/A | R29: #N/A | S29: 30.368333 | T29: #N/A
A30: 19843 | B30: 30955 | C30: #N/A | D30: 2063.1 | E30: #N/A | F30: #N/A | G30: #N/A | H30: 11 | I30: #N/A | J30: 1.3025972 | K30: 2.4061 | L30: #N/A | M30: #N/A | N30: 104.4 | O30: 16.98 | P30: 0.0060729788 | Q30: #N/A | R30: #N/A | S30: 29.104333 | T30: #N/A
A31: 19844 | B31: 31047 | C31: #N/A | D31: 2080.1 | E31: #N/A | F31: #N/A | G31: #N/A | H31: 8.125 | I31: #N/A | J31: 1.3673007 | K31: 2.7075333 | L31: #N/A | M31: #N/A | N31: 105.3 | O31: 17.136667 | P31: 0.0090100711 | Q31: #N/A | R31: #N/A | S31: 27.430667 | T31: #N/A
A32: 19851 | B32: 31137 | C32: #N/A | D32: 2100.2 | E32: #N/A | F32: #N/A | G32: #N/A | H32: 8.5 | I32: #N/A | J32: 1.4618729 | K32: 2.8346667 | L32: #N/A | M32: #N/A | N32: 106.26667 | O32: 17.91 | P32: 0.040991062 | Q32: #N/A | R32: #N/A | S32: 27.05 | T32: #N/A
A33: 19852 | B33: 31228 | C33: #N/A | D33: 2118.7 | E33: #N/A | F33: #N/A | G33: #N/A | H33: 7.75 | I33: #N/A | J33: 1.3773757 | K33: 2.8576333 | L33: #N/A | M33: #N/A | N33: 107.23333 | O33: 18.53 | P33: 0.034841861 | Q33: #N/A | R33: #N/A | S33: 27.857 | T33: #N/A
A34: 19853 | B34: 31320 | C34: #N/A | D34: 2151.1 | E34: #N/A | F34: #N/A | G34: #N/A | H34: 8 | I34: #N/A | J34: 1.2739995 | K34: 2.9208 | L34: #N/A | M34: #N/A | N34: 107.9 | O34: 18.876667 | P34: 0.022633036 | Q34: #N/A | R34: #N/A | S34: 27.791 | T34: #N/A
A35: 19854 | B35: 31412 | C35: #N/A | D35: 2167.1 | E35: #N/A | F35: #N/A | G35: #N/A | H35: 7.75 | I35: #N/A | J35: 1.1713136 | K35: 3.1654333 | L35: #N/A | M35: #N/A | N35: 109 | O35: 19.063333 | P35: 0.0095166401 | Q35: #N/A | R35: #N/A | S35: 29.193 | T35: #N/A
A36: 19861 | B36: 31502 | C36: #N/A | D36: 2187.3 | E36: #N/A | F36: #N/A | G36: #N/A | H36: 7.25 | I36: #N/A | J36: 1.0817094 | K36: 3.2149667 | L36: #N/A | M36: #N/A | N36: 109.56667 | O36: 19.356667 | P36: 0.012038091 | Q36: #N/A | R36: #N/A | S36: 17.001667 | T36: #N/A
A37: 19862 | B37: 31593 | C37: #N/A | D37: 2197.1 | E37: #N/A | F37: #N/A | G37: #N/A | H37: 6.875 | I37: #N/A | J37: 1.0427982 | K37: 3.2090667 | L37: #N/A | M37: #N/A | N37: 109.03333 | O37: 19.406667 | P37: 0.0027180194 | Q37: #N/A | R37: #N/A | S37: 13.92 | T37: #N/A
A38: 19863 | B38: 31685 | C38: #N/A | D38: 2218.2 | E38: #N/A | F38: #N/A | G38: #N/A | H38: 5.875 | I38: #N/A | J38: 0.98696515 | K38: 3.6904667 | L38: #N/A | M38: #N/A | N38: 109.7 | O38: 19.66 | P38: 0.016208381 | Q38: #N/A | R38: 12.316667 | S38: 13.86 | T38: #N/A
A39: 19864 | B39: 31777 | C39: #N/A | D39: 2230.1 | E39: #N/A | F39: #N/A | G39: #N/A | H39: 5.875 | I39: #N/A | J39: 0.96334164 | K39: 3.7295 | L39: #N/A | M39: #N/A | N39: 110.46667 | O39: 20.15 | P39: 0.024416901 | Q39: #N/A | R39: 14.676667 | S39: 15.378333 | T39: #N/A
A40: 19871 | B40: 31867 | C40: #N/A | D40: 2246.6 | E40: #N/A | F40: #N/A | G40: #N/A | H40: 6 | I40: #N/A | J40: 0.88926304 | K40: 3.7314 | L40: #N/A | M40: #N/A | N40: 111.8 | O40: 20.446667 | P40: 0.012528852 | Q40: #N/A | R40: 17.87 | S40: 18.229 | T40: #N/A
A41: 19872 | B41: 31958 | C41: #N/A | D41: 2270.8 | E41: #N/A | F41: #N/A | G41: #N/A | H41: 6.75 | I41: #N/A | J41: 0.86945685 | K41: 3.7314 | L41: #N/A | M41: #N/A | N41: 113.06667 | O41: 20.876667 | P41: 0.021052688 | Q41: #N/A | R41: 18.666667 | S41: 19.364 | T41: #N/A
A42: 19873 | B42: 32050 | C42: #N/A | D42: 2290.5 | E42: #N/A | F42: #N/A | G42: #N/A | H42: 7.3125 | I42: #N/A | J42: 0.88626292 | K42: 3.7314 | L42: #N/A | M42: #N/A | N42: 114.26667 | O42: 21.17 | P42: 0.016297902 | Q42: #N/A | R42: 19.05 | S42: 20.385 | T42: #N/A
A43: 19874 | B43: 32142 | C43: #N/A | D43: 2329.8 | E43: #N/A | F43: #N/A | G43: #N/A | H43: 6.8125 | I43: #N/A | J43: 0.8235039 | K43: 3.7314 | L43: #N/A | M43: #N/A | N43: 115.33333 | O43: 21.78 | P43: 0.027898326 | Q43: #N/A | R43: 17.863333 | S43: 18.669667 | T43: #N/A
A44: 19881 | B44: 32233 | C44: #N/A | D44: 2341.9 | E44: #N/A | F44: #N/A | G44: #N/A | H44: 6.75 | I44: #N/A | J44: 0.81052822 | K44: 3.7314 | L44: #N/A | M44: #N/A | N44: 116.23333 | O44: 22.616667 | P44: 0.038127533 | Q44: #N/A | R44: 15.736667 | S44: 16.714 | T44: #N/A
A45: 19882 | B45: 32324 | C45: #N/A | D45: 2372.7 | E45: #N/A | F45: #N/A | G45: #N/A | H45: 7.4375 | I45: #N/A | J45: 0.82118886 | K45: 3.7314 | L45: #N/A | M45: #N/A | N45: 117.56667 | O45: 23.88 | P45: 0.054896207 | Q45: #N/A | R45: 16.15 | S45: 17.281 | T45: #N/A
A46: 19883 | B46: 32416 | C46: #N/A | D46: 2386.6 | E46: #N/A | F46: #N/A | G46: #N/A | H46: 8.125 | I46: #N/A | J46: 0.89768756 | K46: 3.7314 | L46: #N/A | M46: #N/A | N46: 119 | O46: 25.99 | P46: 0.09000399 | Q46: #N/A | R46: 14.326667 | S46: 15.163 | T46: #N/A
A47: 19884 | B47: 32508 | C47: #N/A | D47: 2418.4 | E47: #N/A | F47: #N/A | G47: #N/A | H47: 8.6875 | I47: #N/A | J47: 0.85469355 | K47: 3.7314 | L47: #N/A | M47: #N/A | N47: 120.3 | O47: 27.7 | P47: 0.064851312 | Q47: #N/A | R47: 13.58 | S47: 14.680333 | T47: #N/A
A48: 19891 | B48: 32598 | C48: #N/A | D48: 2442.9 | E48: #N/A | F48: #N/A | G48: #N/A | H48: 9.75 | I48: #N/A | J48: 0.88794175 | K48: 3.7314 | L48: #N/A | M48: #N/A | N48: 121.66667 | O48: 28.933333 | P48: 0.0457801 | Q48: #N/A | R48: 17.586667 | S48: 18.418 | T48: #N/A
A49: 19892 | B49: 32689 | C49: #N/A | D49: 2461.6 | E49: #N/A | F49: #N/A | G49: #N/A | H49: 9.5625 | I49: #N/A | J49: 0.93001916 | K49: 3.7314 | L49: #N/A | M49: #N/A | N49: 123.63333 | O49: 29.77 | P49: 0.026949376 | Q49: #N/A | R49: 18.873333 | S49: 20.359 | T49: #N/A
... A51: 19894 | B51: 32873 | C51: #N/A | D51: 2484.7 | E51: #N/A | F51: #N/A | G51: #N/A | H51: 8.25 | I51: #N/A | J51: 0.88523255 | K51: 3.8817667 | L51: #N/A | M51: #N/A | N51: 125.86667 | O51: 29.79 | P51: -0.0046807981 | Q51: #N/A | R51: 19.16 | S51: 20.333 | T51: #N/A
A52: 19901 | B52: 32963 | C52: #N/A | D52: 2511.9 | E52: #N/A | F52: #N/A | G52: #N/A | H52: 8.25 | I52: #N/A | J52: 0.82923782 | K52: 4.7339 | L52: #N/A | M52: #N/A | N52: 128.03333 | O52: 30.176667 | P52: 0.015716355 | Q52: 22.223333 | R52: 19.816667 | S52: 21.722333 | T52: #N/A
A53: 19902 | B53: 33054 | C53: #N/A | D53: 2521 | E53: #N/A | F53: #N/A | G53: #N/A | H53: 8.25 | I53: #N/A | J53: 0.81816992 | K53: 4.7339 | L53: #N/A | M53: #N/A | N53: 129.3 | O53: 30.446667 | P53: 0.0055199987 | Q53: 18.773333 | R53: 16.02 | S53: 17.896667 | T53: #N/A
A54: 19903 | B54: 33146 | C54: #N/A | D54: 2522.7 | E54: #N/A | F54: #N/A | G54: #N/A | H54: 8 | I54: #N/A | J54: 0.77100804 | K54: 4.734 | L54: #N/A | M54: #N/A | N54: 131.53333 | O54: 30.503333 | P54: 0.0029427449 | Q54: 25.226667 | R54: 26.413333 | S54: 26.499667 | T54: #N/A
A55: 19904 | B55: 33238 | C55: #N/A | D55: 2499.7 | E55: #N/A | F55: #N/A | G55: #N/A | H55: 7 | I55: #N/A | J55: 0.73163594 | K55: 4.9801667 | L55: #N/A | M55: #N/A | N55: 133.76667 | O55: 30.876667 | P55: 0.012039215 | Q55: 25.96 | R55: 32.453333 | S55: 31.853 | T55: #N/A
A56: 19911 | B56: 33328 | C56: #N/A | D56: 2488 | E56: #N/A | F56: #N/A | G56: #N/A | H56: 6 | I56: #N/A | J56: 0.74585677 | K56: 5.2352 | L56: #N/A | M56: #N/A | N56: 134.76667 | O56: 30.81 | P56: 0.00087818641 | Q56: 22.256667 | R56: 20.73 | S56: 21.780667 | T56: #N/A
A57: 19912 | B57: 33419 | C57: #N/A | D57: 2507.4 | E57: #N/A | F57: #N/A | G57: #N/A | H57: 5.75 | I57: #N/A | J57: 0.84243869 | K57: 5.3230333 | L57: #N/A | M57: #N/A | N57: 135.56667 | O57: 31.373333 | P57: 0.014137821 | Q57: 17.146667 | R57: 18.846667 | S57: 20.752667 | T57: #N/A
A58: 19913 | B58: 33511 | C58: #N/A | D58: 2520.1 | E58: #N/A | F58: #N/A | G58: #N/A | H58: 5.25 | I58: #N/A | J58: 0.84912469 | K58: 5.3762333 | L58: #N/A | M58: #N/A | N58: 136.6 | O58: 31.9 | P58: 0.017944033 | Q58: 16.643333 | R58: 19.89 | S58: 21.655 | T58: #N/A
A59: 19914 | B59: 33603 | C59: #N/A | D59: 2528.8 | E59: #N/A | F59: #N/A | G59: #N/A | H59: 4 | I59: #N/A | J59: 0.79580874 | K59: 5.4047667 | L59: #N/A | M59: #N/A | N59: 137.73333 | O59: 32.283333 | P59: 0.011817548 | Q59: 17.493333 | R59: 20.576667 | S59: 21.736667 | T59: #N/A
A60: 19921 | B60: 33694 | C60: #N/A | D60: 2559.1 | E60: 2111.33 | F60: #N/A | G60: #N/A | H60: 4 | I60: #N/A | J60: 0.79200184 | K60: 5.4755 | L60: #N/A | M60: #N/A | N60: 138.66667 | O60: 32.483333 | P60: 0.009765438 | Q60: 17.56 | R60: 17.946667 | S60: 18.910333 | T60: 9.78
A61: 19922 | B61: 33785 | C61: #N/A | D61: 2586.9 | E61: 2219.2 | F61: 0.04755739 | G61: #N/A | H61: 3.75 | I61: #N/A | J61: 0.78663765 | K61: 5.5057667 | L61: #N/A | M61: #N/A | N61: 139.73333 | O61: 33.126667 | P61: 0.015189491 | Q61: 15.613333 | R61: 19.99 | S61: 21.186 | T61: 9.7633333
A62: 19923 | B62: 33877 | C62: #N/A | D62: 2612.4 | E62: 2303.52 | F62: 0.036748155 | G62: #N/A | H62: 3 | I62: #N/A | J62: 0.72128909 | K62: 5.4676333 | L62: #N/A | M62: #N/A | N62: 140.8 | O62: 33.843333 | P62: 0.022675969 | Q62: 13.906667 | R62: 20.083333 | S62: 21.670333 | T62: 9.78
A63: 19924 | B63: 33969 | C63: #N/A | D63: 2639.7 | E63: 2357.01 | F63: 0.026937562 | G63: #N/A | H63: 3 | I63: #N/A | J63: 0.78883846 | K63: 5.6575333 | L63: #N/A | M63: #N/A | N63: 142.03333 | O63: 34.97 | P63: 0.033419174 | Q63: 14.75 | R63: 19.203333 | S63: 20.479 | T63: 9.8033333
A64: 19931 | B64: 34059 | C64: #N/A | D64: 2644.1 | E64: 2431.35 | F64: 0.032272537 | G64: #N/A | H64: 3 | I64: #N/A | J64: 0.83958592 | K64: 5.7708333 | L64: #N/A | M64: #N/A | N64: 143.06667 | O64: 36.07 | P64: 0.034834188 | Q64: 13.246667 | R64: 18.216667 | S64: 19.825 | T64: 9.7033333
A65: 19932 | B65: 34150 | C65: #N/A | D65: 2659.5 | E65: 2520.19 | F65: 0.033564173 | G65: #N/A | H65: 3 | I65: #N/A | J65: 0.82798821 | K65: 5.7366 | L65: #N/A | M65: #N/A | N65: 144.1 | O65: 37.786667 | P65: 0.043207519 | Q65: 12.99 | R65: 18.276667 | S65: 19.76 | T65: 9.4766667
A66: 19933 | B66: 34242 | C66: #N/A | D66: 2672.2 | E66: 2604.98 | F66: 0.032376747 | G66: #N/A | H66: 3 | I66: #N/A | J66: 0.86936363 | K66: 5.7892333 | L66: #N/A | M66: #N/A | N66: 144.76667 | O66: 39.27 | P66: 0.040087394 | Q66: 12.12 | R66: 16.496667 | S66: 17.796333 | T66: 8.9833333
A67: 19934 | B67: 34334 | C67: #N/A | D67: 2708.5 | E67: 2691.54 | F67: 0.036458774 | G67: #N/A | H67: 3 | I67: #N/A | J67: 0.87678023 | K67: 5.8103 | L67: #N/A | M67: #N/A | N67: 145.96667 | O67: 40.976667 | P67: 0.043648965 | Q67: 12.44 | R67: 15.18 | S67: 16.451333 | T67: 8.2933333
A68: 19941 | B68: 34424 | C68: #N/A | D68: 2734.8 | E68: 2769.84 | F68: 0.029728603 | G68: #N/A | H68: 3.5 | I68: #N/A | J68: 0.88924722 | K68: 8.7236333 | L68: #N/A | M68: #N/A | N68: 146.7 | O68: 44.02 | P68: 0.077386224 | Q68: 13.383333 | R68: 13.97 | S68: 14.813333 | T68: 7.7
A69: 19942 | B69: 34515 | C69: #N/A | D69: 2771.9 | E69: 2861.93 | F69: 0.03106403 | G69: #N/A | H69: 4.25 | I69: #N/A | J69: 0.86030633 | K69: 8.6982 | L69: #N/A | M69: #N/A | N69: 147.53333 | O69: 46.126667 | P69: 0.043952116 | Q69: 14.593333 | R69: 16.06 | S69: 17.776667 | T69: 7.41
A70: 19943 | B70: 34607 | C70: #N/A | D70: 2788.1 | E70: 2950.29 | F70: 0.029805743 | G70: #N/A | H70: 4.75 | I70: #N/A | J70: 0.81511993 | K70: 8.6086 | L70: #N/A | M70: #N/A | N70: 148.9 | O70: 49.33 | P70: 0.069887828 | Q70: 12.533333 | R70: 16.796667 | S70: 18.496667 | T70: 7.5266667
A71: 19944 | B71: 34699 | C71: #N/A | D71: 2820 | E71: 3016.28 | F71: 0.024067757 | G71: #N/A | H71: 5.5 | I71: #N/A | J71: 0.8063519 | K71: 8.5298333 | L71: #N/A | M71: #N/A | N71: 149.76667 | O71: 51.993333 | P71: 0.054751866 | Q71: 15.27 | R71: 16.536667 | S71: 17.656667 | T71: 8.0166667
A72: 19951 | B72: 34789 | C72: 2113963.1 | D72: 2830 | E72: 3092.03 | F72: 0.0264196 | G72: #N/A | H72: 6 | I72: #N/A | J72: 0.78604611 | K72: 8.4548 | L72: #N/A | M72: #N/A | N72: 150.86667 | O72: 53.92 | P72: 0.039180537 | Q72: 11.97 | R72: 16.89 | S72: 18.356667 | T72: 8.6166667
A73: 19952 | B73: 34880 | C73: 2130670.8 | D73: 2838.4 | E73: 3181.7 | F73: 0.027726203 | G73: #N/A | H73: 6 | I73: #N/A | J73: 0.75103079 | K73: 8.3665667 | L73: #N/A | M73: #N/A | N73: 152.1 | O73: 55.3 | P73: 0.02248995 | Q73: 12.203333 | R73: 18.103333 | S73: 19.343333 | T73: 9.0166667
A74: 19953 | B74: 34972 | C74: 2135994.9 | D74: 2862.6 | E74: 3267.58 | F74: 0.025905126 | G74: #N/A | H74: 5.75 | I74: #N/A | J74: 0.76180416 | K74: 8.3278 | L74: #N/A | M74: #N/A | N74: 152.86667 | O74: 56.613333 | P74: 0.024183847 | Q74: 12.456667 | R74: 16.216667 | S74: 17.853333 | T74: 9.06
A75: 19954 | B75: 35064 | C75: 2140682.9 | D75: 2882 | E75: 3339 | F75: 0.021713956 | G75: #N/A | H75: 5.5 | I75: #N/A | J75: 0.75943984 | K75: 8.3345667 | L75: #N/A | M75: #N/A | N75: 153.7 | O75: 57.736667 | P75: 0.020396326 | Q75: 12.86 | R75: 16.966667 | S75: 18.156667 | T75: 8.87
A76: 19961 | B76: 35155 | C76: 2144754.9 | D76: 2903.6 | E76: 3421.05 | F76: 0.026948426 | G76: #N/A | H76: 5.25 | I76: #N/A | J76: 0.77684384 | K76: 8.3405667 | L76: #N/A | M76: #N/A | N76: 155.06667 | O76: 58.933333 | P76: 0.022221824 | Q76: 15.42 | R76: 18.566667 | S76: 19.77 | T76: 8.48
A77: 19962 | B77: 35246 | C77: 2161523.5 | D77: 2952 | E77: 3485.99 | F77: 0.018535317 | G77: #N/A | H77: 5.25 | I77: #N/A | J77: 0.79713033 | K77: 8.3472667 | L77: #N/A | M77: #N/A | N77: 156.4 | O77: 60.39 | P77: 0.022765054 | Q77: 16.376667 | R77: 19.503333 | S77: 21.756667 | T77: 8.1
A78: 19963 | B78: 35338 | C78: 2171466.1 | D78: 2978.5 | E78: 3580.01 | F78: 0.025968132 | G78: #N/A | H78: 5.25 | I78: #N/A | J78: 0.78473225 | K78: 8.3376333 | L78: #N/A | M78: #N/A | N78: 157.3 | O78: 61.126667 | P78: 0.01215841 | Q78: 16.773333 | R78: 20.903333 | S78: 22.423333 | T78: 7.78
A79: 19964 | B79: 35430 | C79: 2183386.6 | D79: 3009.5 | E79: 3679.12 | F79: 0.0252896 | G79: #N/A | H79: 5.25 | I79: #N/A | J79: 0.79248513 | K79: 8.3294333 | L79: #N/A | M79: #N/A | N79: 158.66667 | O79: 61.683333 | P79: 0.0096005442 | Q79: 17.213333 | R79: 23.566667 | S79: 24.666667 | T79: 7.3866667
A80: 19971 | B80: 35520 | C80: 2189616.2 | D80: 3028.9 | E80: 3759.93 | F80: 0.025868699 | G80: #N/A | H80: 5.5 | I80: #N/A | J80: 0.84944206 | K80: 8.3248333 | L80: #N/A | M80: 72.8 | N80: 159.63333 | O80: 61.94 | P80: 0.0050859726 | Q80: 19.926667 | R80: 21.173333 | S80: 22.79 | T80: 7.02
A81: 19972 | B81: 35611 | C81: 2215960.3 | D81: 3079.3 | E81: 3841.64 | F81: 0.021894817 | G81: #N/A | H81: 5.5 | I81: #N/A | J81: 0.87438574 | K81: 8.3236667 | L81: #N/A | M81: 72.846667 | N81: 160 | O81: 62.27 | P81: 0.0044262481 | Q81: 19.923333 | R81: 18.053333 | S81: 19.906667 | T81: 6.6766667
A82: 19973 | B82: 35703 | C82: 2233286.1 | D82: 3117.8 | E82: 3900.04 | F82: 0.01397695 | G82: #N/A | H82: 5.5 | I82: #N/A | J82: 0.91531505 | K82: 8.3173333 | L82: #N/A | M82: 73.186667 | N82: 160.8 | O82: 62.443333 | P82: 0.0025341353 | Q82: 22.473333 | R82: 18.506667 | S82: 19.783333 | T82: 6.3133333
A83: 19974 | B83: 35795 | C83: 2256628.9 | D83: 3144.4 | E83: 3993.49 | F83: 0.020198426 | G83: #N/A | H83: 5.5 | I83: #N/A | J83: 0.88987236 | K83: 8.3114333 | L83: #N/A | M83: 73.483333 | N83: 161.66667 | O83: 62.236667 | P83: -0.0033965009 | Q83: 27.453333 | R83: 18.74 | S83: 19.916667 | T83: 6.0566667
A84: 19981 | B84: 35885 | C84: 2273109.1 | D84: 3175.9 | E84: 4023.94 | F84: 0.012464907 | G84: #N/A | H84: 5.5 | I84: #N/A | J84: 0.92010428 | K84: 8.3080667 | L84: #N/A | M84: 73.556667 | N84: 162 | O84: 62.036667 | P84: -0.0023415342 | Q84: 21.343333 | R84: 14.12 | S84: 15.93 | T84: 5.82
A85: 19982 | B85: 35976 | C85: 2281728 | D85: 3205.3 | E85: 4113.21 | F85: 0.022547287 | G85: #N/A | H85: 5.5 | I85: #N/A | J85: 0.90867237 | K85: 8.3080667 | L85: #N/A | M85: 73.796667 | N85: 162.53333 | O85: 61.846667 | P85: -0.003191469 | Q85: 21.52 | R85: 13.366667 | S85: 14.653333 | T85: 5.5066667
A86: 19983 | B86: 36068 | C86: 2293780.3 | D86: 3245.7 | E86: 4213.53 | F86: 0.023415795 | G86: #N/A | H86: 5.25 | I86: #N/A | J86: 0.89466778 | K86: 8.3085 | L86: #N/A | M86: 73.96 | N86: 163.36667 | O86: 61.566667 | P86: -0.0050379153 | Q86: 29.906667 | R86: 12.443333 | S86: 14.13 | T86: 5.21
A87: 19984 | B87: 36160 | C87: 2300668.1 | D87: 3297.9 | E87: 4365.75 | F87: 0.031394483 | G87: #N/A | H87: 4.75 | I87: #N/A | J87: 0.84978614 | K87: 8.2778667 | L87: #N/A | M87: 74.043333 | N87: 164.13333 | O87: 61.483333 | P87: -0.0017192265 | Q87: 29.436667 | R87: 11.186667 | S87: 12.84 | T87: 4.8333333
A88: 19991 | B88: 36250 | C88: 2323517.7 | D88: 3328.9 | E88: 4371.73 | F88: 0.0067619141 | G88: 2 | H88: 4.75 | I88: #N/A | J88: 0.89024972 | K88: 8.2787333 | L88: #N/A | M88: 74.11 | N88: 164.73333 | O88: 61.086667 | P88: -0.005724322 | Q88: 27.39 | R88: 11.296667 | S88: 13.046667 | T88: 4.5
A89: 19992 | B89: 36341 | C89: 2334547 | D89: 3356.7 | E89: 4437.88 | F89: 0.015409055 | G89: 1.5 | H89: 5 | I89: #N/A | J89: 0.946072 | K89: 8.2785667 | L89: #N/A | M89: 74.493333 | N89: 165.96667 | O89: 60.616667 | P89: -0.0073759222 | Q89: 24.436667 | R89: 15.46 | S89: 17.66 | T89: 4.2766667
A90: 19993 | B90: 36433 | C90: 2365082.6 | D90: 3401.2 | E90: 4541.57 | F90: 0.022403921 | G90: 1.5 | H90: 5.25 | I90: #N/A | J90: 0.95368281 | K90: 8.2774 | L90: #N/A | M90: 74.783333 | N90: 167.2 | O90: 60.87 | P90: 0.0037165633 | Q90: 23.303333 | R90: 20.613333 | S90: 21.736667 | T90: 4.28
A91: 19994 | B91: 36525 | C91: 2389876.2 | D91: 3457 | E91: 4676.15 | F91: 0.025405659 | G91: 2 | H91: 5.5 | I91: #N/A | J91: 0.96293657 | K91: 8.2783667 | L91: #N/A | M91: 75.163333 | N91: 168.43333 | O91: 60.916667 | P91: 0.00013182527 | Q91: 22.626667 | R91: 24.016667 | S91: 24.563333 | T91: 4.53
A92: 20001 | B92: 36616 | C92: 2420575 | D92: 3469.5 | E92: 4736.06 | F92: 0.017260748 | G92: 2.5 | H92: 6 | I92: #N/A | J92: 1.0130132 | K92: 8.2786333 | L92: 8.1466333 | M92: 75.593333 | N92: 170.1 | O92: 61.106667 | P92: 0.0036058551 | Q92: 23.173333 | R92: 26.926667 | S92: 28.806667 | T92: 4.91
A93: 20002 | B93: 36707 | C93: 2442741.1 | D93: 3532.7 | E93: 4843.15 | F93: 0.023339857 | G93: 3.25 | H93: 6.5 | I93: #N/A | J93: 1.0706275 | K93: 8.2782 | L93: 7.7309667 | M93: 75.896667 | N93: 171.43333 | O93: 60.733333 | P93: -0.0054115681 | Q93: 25.023333 | R93: 26.766667 | S93: 28.783333 | T93: 5.2466667
A94: 20003 | B94: 36799 | C94: 2459219.6 | D94: 3536.3 | E94: 4947.25 | F94: 0.020332582 | G94: 3.5 | H94: 6.5 | I94: #N/A | J94: 1.1046355 | K94: 8.2791667 | L94: 7.493 | M94: 76.453333 | N94: 173 | O94: 61.046667 | P94: 0.0046800287 | Q94: 19.223333 | R94: 30.673333 | S94: 31.623333 | T94: 5.4066667
A95: 20004 | B95: 36891 | C95: 2470828.1 | D95: 3557.5 | E95: 5054.9 | F95: 0.018599328 | G95: 3.75 | H95: 6.5 | I95: #N/A | J95: 1.1499271 | K95: 8.2776667 | L95: 7.1978667 | M95: 76.92 | N95: 174.23333 | O95: 61.456667 | P95: 0.0062378424 | Q95: 26.036667 | R95: 29.723333 | S95: 31.98 | T95: 5.4366667
A96: 20011 | B96: 36981 | C96: 2497942.9 | D96: 3545.8 | E96: 5157.77 | F96: 0.023311459 | G96: 3.75 | H96: 5 | I96: #N/A | J96: 1.0832241 | K96: 8.2774 | L96: 7.6411 | M96: 77.096667 | N96: 175.9 | O96: 61.503333 | P96: 0.00085913338 | Q96: 25.61 | R96: 25.873333 | S96: 28.81 | T96: 5.32
A97: 20012 | B97: 37072 | C97: 2499200.4 | D97: 3567.9 | E97: 5254.71 | F97: 0.020161573 | G97: 3.5 | H97: 3.75 | I97: #N/A | J97: 1.1453306 | K97: 8.2770333 | L97: 7.2267667 | M97: 77.84 | N97: 177.13333 | O97: 61.686667 | P97: 0.0036076943 | Q97: 24.003333 | R97: 27.273333 | S97: 27.883333 | T97: 5.2266667
A98: 20013 | B98: 37164 | C98: 2504580 | D98: 3553.6 | E98: 5344.5 | F98: 0.01549141 | G98: 2.75 | H98: 3 | I98: #N/A | J98: 1.1226528 | K98: 8.2769 | L98: 7.3727 | M98: 78.176667 | N98: 177.63333 | O98: 61.55 | P98: -0.002443132 | Q98: 26.416667 | R98: 25.303333 | S98: 26.6 | T98: 5.1566667
A99: 20014 | B99: 37256 | C99: 2503211.8 | D99: 3563.4 | E99: 5463.04 | F99: 0.02082286 | G99: 2.25 | H99: 1.75 | I99: #N/A | J99: 1.1166755 | K99: 8.2767 | L99: 7.4121667 | M99: 78.353333 | N99: 177.5 | O99: 61.373333 | P99: -0.0030070972 | Q99: 27.69 | R99: 19.35 | S99: 20.403333 | T99: 5.0266667
A100: 20021 | B100: 37346 | C100: 2508949.7 | D100: 3593.2 | E100: 5589.31 | F100: 0.023559478 | G100: 2.25 | H100: 1.75 | I100: #N/A | J100: 1.1410658 | K100: 8.2770333 | L100: 7.2537667 | M100: 79.046667 | N100: 178.06667 | O100: 61.136667 | P100: -0.004127858 | Q100: 21.373333 | R100: 21.133333 | S100: 21.61 | T100: 5.01
A101: 20022 | B101: 37437 | C101: 2520693.4 | D101: 3615.2 | E101: 5716.35 | F101: 0.025329885 | G101: 2.25 | H101: 1.75 | I101: #N/A | J101: 1.0876331 | K101: 8.2769667 | L101: 7.6101 | M101: 79.473333 | N101: 179.46667 | O101: 61.02 | P101: -0.0016453087 | Q101: 21.753333 | R101: 25.053333 | S101: 26.27 | T101: 5.0533333
...

Sheet Haver_M
C1: USCPI
A2: 198001 *M | B2: .excel_last | C2: S111PC@G10
A3: .DESC | C3: U.S.: Consumer Price Index (SA, 1982-84=100)
A4: .T1 | C4: Jan-1947
A5: .TN | C5: Apr-2026
A6: .SOURCE | C6: BLS
A7: .LSOURCE | C7: Bureau of Labor Statistics
A8: .AGG | C8: Average
A9: .FRQ | C9: Monthly
A10: .MAG | C10: 0
A11: .GEO2 | C11: Not Defined
A12: 198001 | B12: 29251 | C12: 78
A13: 198002 | B13: 29280 | C13: 79
A14: 198003 | B14: 29311 | C14: 80.1
A15: 198004 | B15: 29341 | C15: 80.9
A16: 198005 | B16: 29372 | C16: 81.7
A17: 198006 | B17: 29402 | C17: 82.5
A18: 198007 | B18: 29433 | C18: 82.6
A19: 198008 | B19: 29464 | C19: 83.2
A20: 198009 | B20: 29494 | C20: 83.9
A21: 198010 | B21: 29525 | C21: 84.7
A22: 198011 | B22: 29555 | C22: 85.6
A23: 198012 | B23: 29586 | C23: 86.4
... A560: 202509 | B560: 45930 | C560: 324.245
A561: 202510 | B561: 45961 | C561: #N/A
A562: 202511 | B562: 45991 | C562: 325.063
A563: 202512 | B563: 46022 | C563: 326.031 | D563: =AVERAGE(C562:C563) -> 325.547
A564: 202601 | B564: 46053 | C564: 326.588
A565: 202602 | B565: 46081 | C565: 327.46
A566: 202603 | B566: 46112 | C566: 330.293
A567: 202604 | B567: 46142 | C567: 332.407
A568: 202605 | B568: 46173 | C568: #N/A

Sheet OEM
A1: Location | B1: China | C1: Eurozone | D1: United States | E1: China | F1: Eurozone | G1: United States | H1: China
A2: Indicator | B2: Interest rate, central bank policy | C2: Interest rate, central bank policy | D2: Interest rate, central bank policy | E2: GDP, real, seasonally adjusted, LCU | F2: GDP, real, seasonally adjusted, LCU | G2: GDP, real, seasonally adjusted, LCU | H2: Consumer price index
A3: Scenario | B3: Sep25_2 25yr | C3: Sep25_2 25yr | D3: Sep25_2 25yr | E3: Sep25_2 25yr | F3: Sep25_2 25yr | G3: Sep25_2 25yr | H3: Sep25_2 25yr
A4: Units | B4: % | C4: % | D4: % | E4: Yuan | F4: Euro | G4: US$ | H4: Index
A5: Scale | B5: NA | C5: NA | D5: NA | E5: Billions | F5: Billions | G5: Billions | H5: NA
A6: Measurement | B6: Level | C6: Level | D6: Level | E6: Level | F6: Level | G6: Level | H6: Level
A7: 1980 Q1 | B7: 0.001 | C7: 0.001 | D7: 13.93896 | E7: 719.647 | F7: 1561.599 | G7: 1835.4 | H7: 16.1549
A8: 1980 Q2 | B8: 0.001 | C8: 0.001 | D8: 11.7426 | E8: 734.2954 | F8: 1554.268 | G8: 1797.575 | H8: 16.2807
A9: 1980 Q3 | B9: 0.001 | C9: 0.001 | D9: 9.094363 | E9: 748.4635 | F9: 1553.382 | G9: 1795.425 | H9: 15.72297
A10: 1980 Q4 | B10: 0.001 | C10: 0.001 | D10: 14.72999 | E10: 764.0247 | F10: 1554.111 | G10: 1828.925 | H10: 15.98073
A11: 1981 Q1 | B11: 0.001 | C11: 0.001 | D11: 15.40231 | E11: 754.6949 | F11: 1555.611 | G11: 1864.75 | H11: 16.55324
A12: 1981 Q2 | B12: 0.001 | C12: 0.001 | D12: 16.51873 | E12: 771.1904 | F12: 1560.27 | G12: 1850.925 | H12: 16.68214
A13: 1981 Q3 | B13: 0.001 | C13: 0.001 | D13: 16.47078 | E13: 787.2404 | F13: 1564.575 | G13: 1873.1 | H13: 16.11065
A14: 1981 Q4 | B14: 0.001 | C14: 0.001 | D14: 12.66561 | E14: 804.7195 | F14: 1568.246 | G14: 1852.7 | H14: 16.37477
A15: 1982 Q1 | B15: 0.001 | C15: 0.001 | D15: 13.27632 | E15: 820.2949 | F15: 1574.728 | G15: 1823.9 | H15: 16.87782
A16: 1982 Q2 | B16: 0.001 | C16: 0.001 | D16: 13.51189 | E16: 839.2487 | F16: 1576.846 | G16: 1832.225 | H16: 17.00924
A17: 1982 Q3 | B17: 0.001 | C17: 0.001 | D17: 10.25 | E17: 859.0854 | F17: 1568.435 | G17: 1825.225 | H17: 16.42655
A18: 1982 Q4 | B18: 0.001 | C18: 0.001 | D18: 9.189394 | E18: 879.734 | F18: 1569.108 | G18: 1825.95 | H18: 16.69584
... A230: 2035 Q4 | B230: 1.199933 | C230: 2.149925 | D230: 3.124914 | E230: 47612.21 | F230: 3694.99 | G230: 7294.975 | H230: 115.9576
A231: Source | B231: People's Bank of China / Haver Analytics | C231: European Central Bank \Haver Analytics | D231: Federal Reserve Board \Haver Analytics | E231: China National Bureau of Statistics\Haver Analytics | F231: Statistical Office of the European Communities\Euro Area Business Cycle Network\Haver Analytics | G231: Bureau of Economic Analysis\Haver Analytics | H231: China National Bureau of Statistics\Haver Analytics
A232: Seasonally adjusted | B232: FALSE | C232: FALSE | D232: FALSE | E232: TRUE | F232: TRUE | G232: TRUE | H232: FALSE
A233: Base year price | B233: NA | C233: NA | D233: NA | E233: 2020 | F233: chained 2020 | G233: chained 2017 | H233: NA
A234: Base year index | B234: NA | C234: NA | D234: NA | E234: NA | F234: NA | G234: NA | H234: 2020
A235: Historical end year | B235: 2025 | C235: 2025 | D235: 2025 | E235: 2025 | F235: 2025 | G235: 2025 | H235: 2025
A236: Historical end quarter | B236: 2 | C236: 2 | D236: 2 | E236: 2 | F236: 2 | G236: 2 | H236: 2
A237: Date of last update | B237: NA | C237: NA | D237: NA | E237: NA | F237: NA | G237: NA | H237: NA
A238: Source details | B238: R9247DL@INTDAILY | C238: agg(R023RM@INTDAILY,avg), spliced with I023M@EUDATA pre-1999 | D238: FFEDTAR@DAILY | E238: GDP, real, LCU (Seasonally adjusted by Oxford Economics) | F238: J025GDPU@EUDATA/1000 | G238: GDPH@USNA / 4 | H238: 2020=100, grown by N924PCY@EMERGEPR
A239: Additional source details | B239: China: PBoC OMO:7 Days Reverse Repurchase: Reference Yield (%p.a.) | C239: Euro-Area: Main Refinancing Operation on Effective Date (%) | D239: Effective federal funds rate prior to 1982Q4; Federal funds target rate or mid-point from 1982Q4 (H.15 Item 1) | E239: NA | F239: EA19: Gross Domestic Product (SWDA, Mil.Ch.2020.EUR-ECU) /1000 | G239: Real Gross Domestic Product (SAAR, Bil.Chn.2017$) / 4 | H239: 2020=100 grown by China: Consumer Price Index (NSA, year/year % chg)
A240: Location code | B240: CHINA | C240: EURO_11 | D240: US | E240: CHINA | F240: EURO_11 | G240: US | H240: CHINA
A241: Indicator code | B241: RCB | C241: RCB | D241: RCB | E241: GDPSA | F241: GDPSA | G241: GDPSA | H241: CPI
A242: Databank code | B242: /oxford-economics/releases/GEM/Sep25_2 25yr | C242: /oxford-economics/releases/GEM/Sep25_2 25yr | D242: /oxford-economics/releases/GEM/Sep25_2 25yr | E242: /oxford-economics/releases/GEM/Sep25_2 25yr | F242: /oxford-economics/releases/GEM/Sep25_2 25yr | G242: /oxford-economics/releases/GEM/Sep25_2 25yr | H242: /oxford-economics/releases/GEM/Sep25_2 25yr

Sheet OEM_aux
A1: Location | B1: China | C1: China
A2: Indicator | B2: Interest rate, central bank policy | C2: Exchange rate, period average, per Euro
A3: Scenario | B3: Jul25_2 25yr | C3: Jul25_2 25yr
A4: Units | B4: % | C4: Yuan per Euro
A5: Scale | B5: NA | C5: NA
A6: Measurement | B6: Level | C6: Level
A7: 1980 Q1 | B7: 3.466667 | C7: 2.137539
A8: 1980 Q2 | B8: 3.466667 | C8: 2.087486
A9: 1980 Q3 | B9: 3.466667 | C9: 2.083947
A10: 1980 Q4 | B10: 3.466667 | C10: 2.027264
A11: 1981 Q1 | B11: 3.466667 | C11: 1.967676
A12: 1981 Q2 | B12: 3.466667 | C12: 1.913917
A13: 1981 Q3 | B13: 3.466667 | C13: 1.823786
A14: 1981 Q4 | B14: 3.466667 | C14: 1.896846
A15: 1982 Q1 | B15: 5.626667 | C15: 1.875449
A16: 1982 Q2 | B16: 5.626667 | C16: 1.85888
A17: 1982 Q3 | B17: 5.626667 | C17: 1.842025
A18: 1982 Q4 | B18: 5.626667 | C18: 1.840952
... A230: 2035 Q4 | B230: 1.999919 | C230: 7.854873
A231: Source | B231: People's Bank of China\Haver Analytics | C231: Oxford Economics calculation
A232: Seasonally adjusted | B232: FALSE | C232: FALSE
A233: Base year price | B233: NA | C233: NA
A234: Base year index | B234: NA | C234: NA
A235: Historical end year | B235: 2024 | C235: NA
A236: Historical end quarter | B236: 4 | C236: NA
A237: Date of last update | B237: NA | C237: NA
A238: Source details | B238: N924FSY1@EMERGEPR, avg, extended back with RLEND | C238: Exchange rate, period average * Exchange rate, period average, Eurozone
A239: Additional source details | B239: China: Medium Term Lending Facility Rate: One Year | C239: NA
A240: Location code | B240: CHINA | C240: CHINA
A241: Indicator code | B241: RCB | C241: RXEURO
A242: Databank code | B242: /oxford-economics/releases/GEM/Jul25_2 25yr | C242: /oxford-economics/releases/GEM/Jul25_2 25yr

Sheet AWM
A1: date | B1: YER | C1: STN | D1: HICP
A2: 25628 | B2: =[3]AWMD_Updated!B2 -> 1099492.8 | C2: =[3]AWMD_Updated!AI2 -> 7.9869932 | D2: =[3]AWMD_Updated!T2 -> 14.274151
A3: 25720 | B3: =[3]AWMD_Updated!B3 -> 1120627.1 | C3: =[3]AWMD_Updated!AI3 -> 7.956545 | D3: =[3]AWMD_Updated!T3 -> 14.434899
A4: 25812 | B4: =[3]AWMD_Updated!B4 -> 1134128 | C4: =[3]AWMD_Updated!AI4 -> 7.6021888 | D4: =[3]AWMD_Updated!T4 -> 14.568972
A5: 25903 | B5: =[3]AWMD_Updated!B5 -> 1147866.6 | C5: =[3]AWMD_Updated!AI5 -> 7.2423084 | D5: =[3]AWMD_Updated!T5 -> 14.752619
A6: 25993 | B6: =[3]AWMD_Updated!B6 -> 1145859.6 | C6: =[3]AWMD_Updated!AI6 -> 6.5168982 | D6: =[3]AWMD_Updated!T6 -> 15.02285
A7: 26085 | B7: =[3]AWMD_Updated!B7 -> 1160538.2 | C7: =[3]AWMD_Updated!AI7 -> 5.9386375 | D7: =[3]AWMD_Updated!T7 -> 15.276236
A8: 26177 | B8: =[3]AWMD_Updated!B8 -> 1178637.9 | C8: =[3]AWMD_Updated!AI8 -> 6.2262126 | D8: =[3]AWMD_Updated!T8 -> 15.456065
A9: 26268 | B9: =[3]AWMD_Updated!B9 -> 1188012.4 | C9: =[3]AWMD_Updated!AI9 -> 6.0058233 | D9: =[3]AWMD_Updated!T9 -> 15.690365
A10: 26359 | B10: =[3]AWMD_Updated!B10 -> 1205616.5 | C10: =[3]AWMD_Updated!AI10 -> 5.0466009 | D10: =[3]AWMD_Updated!T10 -> 15.955659
A11: 26451 | B11: =[3]AWMD_Updated!B11 -> 1213734.5 | C11: =[3]AWMD_Updated!AI11 -> 4.7536779 | D11: =[3]AWMD_Updated!T11 -> 16.183553
A12: 26543 | B12: =[3]AWMD_Updated!B12 -> 1230330.7 | C12: =[3]AWMD_Updated!AI12 -> 4.8573329 | D12: =[3]AWMD_Updated!T12 -> 16.47098
A13: 26634 | B13: =[3]AWMD_Updated!B13 -> 1248340.6 | C13: =[3]AWMD_Updated!AI13 -> 6.394843 | D13: =[3]AWMD_Updated!T13 -> 16.809797
... A221: 45627 | B221: =[3]AWMD_Updated!B221 -> 3250018.1 | C221: =[3]AWMD_Updated!AI221 -> 2.9964872 | D221: =[3]AWMD_Updated!T221 -> 126.92
A222: 45717 | C222: =[3]AWMD_Updated!AI222 -> 2.6140402 | D222: =[3]AWMD_Updated!T222 -> 127.35333

Sheet Mater_M
B1: EZ10Y_M | C1: EZ10Y_M_Avg
B2: Sovereign 10y (%)
A3: 29221
A4: 29252 | B4: =VLOOKUP($A4,[4]BASE_M!$A:$AZ,MATCH(B$2,[4]BASE_M!$4:$4,0),FALSE) -> 8.394
A5: 29281 | B5: =VLOOKUP($A5,[4]BASE_M!$A:$AZ,MATCH(B$2,[4]BASE_M!$4:$4,0),FALSE) -> 9.372
A6: 29312 | B6: =VLOOKUP($A6,[4]BASE_M!$A:$AZ,MATCH(B$2,[4]BASE_M!$4:$4,0),FALSE) -> 9.36 | C6: =AVERAGE(B4:B6) -> 9.042
A7: 29342 | B7: =VLOOKUP($A7,[4]BASE_M!$A:$AZ,MATCH(B$2,[4]BASE_M!$4:$4,0),FALSE) -> 8.594 | C7: =AVERAGE(B5:B7) -> 9.1086667
A8: 29373 | B8: =VLOOKUP($A8,[4]BASE_M!$A:$AZ,MATCH(B$2,[4]BASE_M!$4:$4,0),FALSE) -> 8.18 | C8: =AVERAGE(B6:B8) -> 8.7113333
A9: 29403 | B9: =VLOOKUP($A9,[4]BASE_M!$A:$AZ,MATCH(B$2,[4]BASE_M!$4:$4,0),FALSE) -> 7.954 | C9: =AVERAGE(B7:B9) -> 8.2426667
A10: 29434 | B10: =VLOOKUP($A10,[4]BASE_M!$A:$AZ,MATCH(B$2,[4]BASE_M!$4:$4,0),FALSE) -> 7.839 | C10: =AVERAGE(B8:B10) -> 7.991
A11: 29465 | B11: =VLOOKUP($A11,[4]BASE_M!$A:$AZ,MATCH(B$2,[4]BASE_M!$4:$4,0),FALSE) -> 8.174 | C11: =AVERAGE(B9:B11) -> 7.989
A12: 29495 | B12: =VLOOKUP($A12,[4]BASE_M!$A:$AZ,MATCH(B$2,[4]BASE_M!$4:$4,0),FALSE) -> 8.361 | C12: =AVERAGE(B10:B12) -> 8.1246667
A13: 29526 | B13: =VLOOKUP($A13,[4]BASE_M!$A:$AZ,MATCH(B$2,[4]BASE_M!$4:$4,0),FALSE) -> 8.704 | C13: =AVERAGE(B11:B13) -> 8.413
A14: 29556 | B14: =VLOOKUP($A14,[4]BASE_M!$A:$AZ,MATCH(B$2,[4]BASE_M!$4:$4,0),FALSE) -> 8.861 | C14: =AVERAGE(B12:B14) -> 8.642
A15: 29587 | B15: =VLOOKUP($A15,[4]BASE_M!$A:$AZ,MATCH(B$2,[4]BASE_M!$4:$4,0),FALSE) -> 8.98 | C15: =AVERAGE(B13:B15) -> 8.8483333
A16: 29618 | B16: =VLOOKUP($A16,[4]BASE_M!$A:$AZ,MATCH(B$2,[4]BASE_M!$4:$4,0),FALSE) -> 9.759 | C16: =AVERAGE(B14:B16) -> 9.2
A17: 29646 | B17: =VLOOKUP($A17,[4]BASE_M!$A:$AZ,MATCH(B$2,[4]BASE_M!$4:$4,0),FALSE) -> 10.084 | C17: =AVERAGE(B15:B17) -> 9.6076667
... A614: 47818 | B614: =VLOOKUP($A614,[4]BASE_M!$A:$AZ,MATCH(B$2,[4]BASE_M!$4:$4,0),FALSE) -> 3.25 | C614: =AVERAGE(B612:B614) -> 3.25

Sheet Mater_Q
B1: EZ10Y
B2: Sovereign 10y (%)
A3: 29281
A4: 29373 | B4: =VLOOKUP($A4,Mater_M!A:AR,3,FALSE) -> 8.7113333
A5: 29465 | B5: =VLOOKUP($A5,Mater_M!A:AR,3,FALSE) -> 7.989
A6: 29556 | B6: =VLOOKUP($A6,Mater_M!A:AR,3,FALSE) -> 8.642
A7: 29646 | B7: =VLOOKUP($A7,Mater_M!A:AR,3,FALSE) -> 9.6076667
A8: 29738 | B8: =VLOOKUP($A8,Mater_M!A:AR,3,FALSE) -> 10.304333
A9: 29830 | B9: =VLOOKUP($A9,Mater_M!A:AR,3,FALSE) -> 10.558667
A10: 29921 | B10: =VLOOKUP($A10,Mater_M!A:AR,3,FALSE) -> 9.9646667
A11: 30011 | B11: =VLOOKUP($A11,Mater_M!A:AR,3,FALSE) -> 9.6733333
A12: 30103 | B12: =VLOOKUP($A12,Mater_M!A:AR,3,FALSE) -> 8.9833333
A13: 30195 | B13: =VLOOKUP($A13,Mater_M!A:AR,3,FALSE) -> 8.9873333
A14: 30286 | B14: =VLOOKUP($A14,Mater_M!A:AR,3,FALSE) -> 8.2193333
A15: 30376 | B15: =VLOOKUP($A15,Mater_M!A:AR,3,FALSE) -> 7.6146667
... A186: 45992 | B186: =VLOOKUP($A186,Mater_M!A:AR,3,FALSE) -> 2.7173333

Sheet SA R
B1: CHCPI OEM | C1: Desestacionalizado con R
A2: 29311 | B2: =OEM!H7 -> 16.1549 | C2: 15.848275
A3: 29402 | B3: =OEM!H8 -> 16.2807 | C3: 15.993708
A4: 29494 | B4: =OEM!H9 -> 15.72297 | C4: 16.095644
A5: 29586 | B5: =OEM!H10 -> 15.98073 | C5: 16.200947
A6: 29676 | B6: =OEM!H11 -> 16.55324 | C6: 16.316586
A7: 29767 | B7: =OEM!H12 -> 16.68214 | C7: 16.325678
A8: 29859 | B8: =OEM!H13 -> 16.11065 | C8: 16.483134
A9: 29951 | B9: =OEM!H14 -> 16.37477 | C9: 16.595976
A10: 30041 | B10: =OEM!H15 -> 16.87782 | C10: 16.60842
A11: 30132 | B11: =OEM!H16 -> 17.00924 | C11: 16.68157
A12: 30224 | B12: =OEM!H17 -> 16.42655 | C12: 16.800222
A13: 30316 | B13: =OEM!H18 -> 16.69584 | C13: 16.923685
... A183: 45838 | B183: =OEM!H188 -> 102.8767 | C183: 103.25252

Sheet UK_HAVER
A1: 801 *Q | B1: .excel_last | C1: ABMIQ@UK | D1: UNBEDR@UK | E1: SA(D7BT@UK) | F1: N112XUSV@G10
A2: .DESC | C2: UK: Real Gross Domestic Product (SA, Mil.Chn.2023.GBP) | D2: UK: Official Bank Rate (Average, %) | E2: UK: Consumer Price Index: All Items (NSA, 2015=100) - Seasonal Adjustment, All | F2: U.K.: Exchange Rate (Avg, US$/Pound)
A3: .T1 | C3: Q1-1955 | D3: Q1-1948 <- Jan-1948 | E3: Q1-1988 <- Jan-1988 | F3: Q1-1947 <- Jan-1947
A4: .TN | C4: Q1-2026 | D4: Q1-2026 <- May-2026 | E4: Q1-2026 <- Apr-2026 | F4: Q1-2026 <- May-2026
A5: .LSOURCE | C5: Office for National Statistics | D5: Bank of England | E5: Office for National Statistics | F5: Federal Reserve Board
A6: .AGG | C6: Sum | D6: Average | E6: Average | F6: Average
A7: .DTLM | C7: May-14-2026 08:16 | D7: Jun-01-2026 14:52 | E7: May-20-2026 08:03 | F7: Jun-01-2026 22:28
A8: .FRQ | C8: Quarterly | D8: Quarterly <- Monthly | E8: Quarterly <- Monthly | F8: Quarterly <- Monthly
A9: .DATA_TYPE | C9: LocCur | D9: % | E9: INDEX | F9: US$/LC
A10: .MAG | C10: 6 | D10: 0 | E10: 0 | F10: 0
A11: .GRP | C11: W31 | D11: P50 | E11: P29 | F11: A04
A12: .GRPDESC | C12: UK: GDP (2nd Release) Press Release, ONS, Quarterly | D12: U.K.: Interbank Rates, BoE, Monthly | E12: UK: Consumer Prices Indexes, ONS, Monthly | F12: U.S.: Spot Exchange Rates, FRB G.5, Monthly
A13: .GEO | C13: 112 | D13: 112 | E13: 112 | F13: 111
A14: 801 | B14: 29311 | C14: 290378 | D14: 17 | E14: #N/A | F14: 2.2525667
A15: 802 | B15: 29402 | C15: 284713 | D15: 17 | E15: #N/A | F15: 2.2824333
A16: 803 | B16: 29494 | C16: 284402 | D16: 16.03 | E16: #N/A | F16: 2.3816
A17: 804 | B17: 29586 | C17: 281496 | D17: 15.2 | E17: #N/A | F17: 2.3855
A18: 811 | B18: 29676 | C18: 281257 | D18: 13.546667 | E18: #N/A | F18: 2.3096333
A19: 812 | B19: 29767 | C19: 282155 | D19: 12 | E19: #N/A | F19: 2.0791667
A20: 813 | B20: 29859 | C20: 285437 | D20: 12.513333 | E20: #N/A | F20: 1.8362
A21: 814 | B21: 29951 | C21: 285814 | D21: 14.61 | E21: #N/A | F21: 1.8821667
A22: 821 | B22: 30041 | C22: 286275 | D22: 13.793333 | E22: #N/A | F22: 1.8461
A23: 822 | B23: 30132 | C23: 289232 | D23: 13.016667 | E23: #N/A | F23: 1.7795667
A24: 823 | B24: 30224 | C24: 289852 | D24: 11.353333 | E24: #N/A | F24: 1.7241333
A25: 824 | B25: 30316 | C25: 291832 | D25: 9.6833333 | E25: #N/A | F25: 1.6481
... A45: 874 | B45: 32142 | C45: 357439 | D45: 9.0266667 | E45: #N/A | F45: 1.7554
A46: 881 | B46: 32233 | C46: 363267 | D46: 8.6333333 | E46: 48.806511 | F46: 1.7973667
A47: 882 | B47: 32324 | C47: 365209 | D47: 7.9533333 | E47: 49.226184 | F47: 1.8415
A48: 883 | B48: 32416 | C48: 369774 | D48: 10.89 | E48: 49.862458 | F48: 1.6952
A49: 884 | B49: 32508 | C49: 372752 | D49: 12.273333 | E49: 50.533578 | F49: 1.7910333
A50: 891 | B50: 32598 | C50: 374612 | D50: 12.88 | E50: 51.259161 | F50: 1.7468333
A51: 892 | B51: 32689 | C51: 376951 | D51: 13.223333 | E51: 51.840861 | F51: 1.6281667
A52: 893 | B52: 32781 | C52: 377573 | D52: 13.76 | E52: 52.427737 | F52: 1.5976667
A53: 894 | B53: 32873 | C53: 377508 | D53: 14.81 | E53: 53.331518 | F53: 1.5855
A54: 901 | B54: 32963 | C54: 379458 | D54: 14.88 | E54: 54.222591 | F54: 1.6572667
A55: 902 | B55: 33054 | C55: 381997 | D55: 14.88 | E55: 55.277047 | F55: 1.6749667
A56: 903 | B56: 33146 | C56: 377831 | D56: 14.88 | E56: 56.360326 | F56: 1.8635
A57: 904 | B57: 33238 | C57: 375916 | D57: 13.95 | E57: 57.530704 | F57: 1.9439
... A198: 261 | B198: 46112 | C198: 710896 | D198: 3.75 | E198: 140.82497 | F198: 1.3484667

Sheet reconstruct_levels_ch
A1: date | B1: level CHCPI | C1: diff CPI SA | D1: level reconstructed | G1: level CHGDP | H1: DIFF gdp sa | I1: LEVEL RECONST
A2: 29281
A3: 29373
A4: 29465
A5: 29556
A6: 29646
A7: 29738
A8: 29830
A9: 29921
A10: 30011
A11: 30103
A12: 30195
A13: 30286
... A17: 30651
A18: 30742 | B18: =Haver!O28 -> 16.84
A19: 30834 | B19: =Haver!O29 -> 16.95 | C19: =Haver!P29 -> 0.0067228861 | D19: =B18*(1+C19) -> 16.953213
A20: 30926 | B20: =Haver!O30 -> 16.98 | C20: =Haver!P30 -> 0.0060729788 | D20: =D19*(1+C20) -> 17.05617
A21: 31017 | B21: =Haver!O31 -> 17.136667 | C21: =Haver!P31 -> 0.0090100711 | D21: =D20*(1+C21) -> 17.209847
A22: 31107 | B22: =Haver!O32 -> 17.91 | C22: =Haver!P32 -> 0.040991062 | D22: =D21*(1+C22) -> 17.915297
A23: 31199 | B23: =Haver!O33 -> 18.53 | C23: =Haver!P33 -> 0.034841861 | D23: =D22*(1+C23) -> 18.539499
A24: 31291 | B24: =Haver!O34 -> 18.876667 | C24: =Haver!P34 -> 0.022633036 | D24: =D23*(1+C24) -> 18.959105
A25: 31382 | B25: =Haver!O35 -> 19.063333 | C25: =Haver!P35 -> 0.0095166401 | D25: =D24*(1+C25) -> 19.139532
A26: 31472 | B26: =Haver!O36 -> 19.356667 | C26: =Haver!P36 -> 0.012038091 | D26: =D25*(1+C26) -> 19.369935
A27: 31564 | B27: =Haver!O37 -> 19.406667 | C27: =Haver!P37 -> 0.0027180194 | D27: =D26*(1+C27) -> 19.422583
A28: 31656 | B28: =Haver!O38 -> 19.66 | C28: =Haver!P38 -> 0.016208381 | D28: =D27*(1+C28) -> 19.737391
A29: 31747 | B29: =Haver!O39 -> 20.15 | C29: =Haver!P39 -> 0.024416901 | D29: =D28*(1+C29) -> 20.219317
A30: 31837 | B30: =Haver!O40 -> 20.446667 | C30: =Haver!P40 -> 0.012528852 | D30: =D29*(1+C30) -> 20.472642
A31: 31929 | B31: =Haver!O41 -> 20.876667 | C31: =Haver!P41 -> 0.021052688 | D31: =D30*(1+C31) -> 20.903646
... A49: 33573 | B49: =Haver!O59 -> 32.283333 | C49: =Haver!P59 -> 0.011817548 | D49: =D48*(1+C49) -> 32.338296
A50: 33664 | B50: =Haver!O60 -> 32.483333 | C50: =Haver!P60 -> 0.009765438 | D50: =D49*(1+C50) -> 32.654094 | G50: =Haver!E60 -> 2111.33 | I50: 2111.33
A51: 33756 | B51: =Haver!O61 -> 33.126667 | C51: =Haver!P61 -> 0.015189491 | D51: =D50*(1+C51) -> 33.150093 | H51: =Haver!F61 -> 0.04755739 | I51: =G50*(1+H51) -> 2211.7393
A52: 33848 | B52: =Haver!O62 -> 33.843333 | C52: =Haver!P62 -> 0.022675969 | D52: =D51*(1+C52) -> 33.901803 | H52: =Haver!F62 -> 0.036748155 | I52: =I51*(1+H52) -> 2293.0167
A53: 33939 | B53: =Haver!O63 -> 34.97 | C53: =Haver!P63 -> 0.033419174 | D53: =D52*(1+C53) -> 35.034773 | H53: =Haver!F63 -> 0.026937562 | I53: =I52*(1+H53) -> 2354.785
A54: 34029 | B54: =Haver!O64 -> 36.07 | C54: =Haver!P64 -> 0.034834188 | D54: =D53*(1+C54) -> 36.255181 | H54: =Haver!F64 -> 0.032272537 | I54: =I53*(1+H54) -> 2430.7798
A55: 34121 | B55: =Haver!O65 -> 37.786667 | C55: =Haver!P65 -> 0.043207519 | D55: =D54*(1+C55) -> 37.821678 | H55: =Haver!F65 -> 0.033564173 | I55: =I54*(1+H55) -> 2512.367
A56: 34213 | B56: =Haver!O66 -> 39.27 | C56: =Haver!P66 -> 0.040087394 | D56: =D55*(1+C56) -> 39.33785 | H56: =Haver!F66 -> 0.032376747 | I56: =I55*(1+H56) -> 2593.7092
A57: 34304 | B57: =Haver!O67 -> 40.976667 | C57: =Haver!P67 -> 0.043648965 | D57: =D56*(1+C57) -> 41.054907 | H57: =Haver!F67 -> 0.036458774 | I57: =I56*(1+H57) -> 2688.2727
A58: 34394 | B58: =Haver!O68 -> 44.02 | C58: =Haver!P68 -> 0.077386224 | D58: =D57*(1+C58) -> 44.231991 | H58: =Haver!F68 -> 0.029728603 | I58: =I57*(1+H58) -> 2768.1913
A59: 34486 | B59: =Haver!O69 -> 46.126667 | C59: =Haver!P69 -> 0.043952116 | D59: =D58*(1+C59) -> 46.17608 | H59: =Haver!F69 -> 0.03106403 | I59: =I58*(1+H59) -> 2854.1825
A60: 34578 | B60: =Haver!O70 -> 49.33 | C60: =Haver!P70 -> 0.069887828 | D60: =D59*(1+C60) -> 49.403226 | H60: =Haver!F70 -> 0.029805743 | I60: =I59*(1+H60) -> 2939.2535
A61: 34669 | B61: =Haver!O71 -> 51.993333 | C61: =Haver!P71 -> 0.054751866 | D61: =D60*(1+C61) -> 52.108145 | H61: =Haver!F71 -> 0.024067757 | I61: =I60*(1+H61) -> 3009.9947
A62: 34759 | B62: =Haver!O72 -> 53.92 | C62: =Haver!P72 -> 0.039180537 | D62: =D61*(1+C62) -> 54.14977 | H62: =Haver!F72 -> 0.0264196 | I62: =I61*(1+H62) -> 3089.5176
A63: 34851 | B63: =Haver!O73 -> 55.3 | C63: =Haver!P73 -> 0.02248995 | D63: =D62*(1+C63) -> 55.367596 | H63: =Haver!F73 -> 0.027726203 | I63: =I62*(1+H63) -> 3175.1782
... A186: 46082 | B186: =Haver!O196 -> 100.50667 | C186: =Haver!P196 -> 0.0021913592 | D186: =D185*(1+C186) -> 100.84782 | H186: =Haver!F196 -> 0.016040766 | I186: =I185*(1+H186) -> 34702.784
